Workbook

Sheet Sheet1
A1: Family | B1: What type of song is this? | C1: What region are you searching in? | D1: Enter the name of the culture this song was collected from. | E1: Glottocode_1 | F1: Glottocode_2 | G1: Glottocode_Final | H1: Family Glottocode | I1: Level | J1: Agree? | K1: Common Subfamily? | L1: Common Family? | M1: Notes | N1: ISOcode | O1: Classification Type | P1: Are you sure? | Q1: Enter the track name, as it appears in the source. | R1: Paste a hyperlink here that gets to the source material (e.g., the CD containing the track). | S1: List the track number of the song. | T1: What source(s) is this song listed in? | U1: Is there any secondary function for this song? | V1: Is this an unpublished track that came directly from an anthropologist? | W1: Name | X1: Affiliation | Y1: Email | Z1: Tell us about how you categorized this song. | AA1: Enter the label of the song here. | AB1: Information from ethnography | AC1: Information from lyrics | AD1: If necessary, provide additional information here about how to find this track. | AE1: Confirm here that you did not listen to the song until this point! | AF1: Is there at least one audible singer on the recording? | AG1: How easy is it to hear the singer(s)? | AH1: Do you have access to the audio of this song? | AI1: General notes | AJ1: Timestamp | AK1: What are your initials?
A2: =VLOOKUP(H2,Languages!$A$2:$B$430,2,FALSE) -> Abkhaz-Adyge | B2: Dance | C2: Caucasus | D2: Abkhazia | E2: abkh1244 | F2: abkh1244 | G2: abkh1244 | H2: =VLOOKUP(G2,'languoid 4.0'!$A$1:$I$24439,2,FALSE) -> abkh1242 | I2: =VLOOKUP(G2,'languoid 4.0'!$A$1:$I$24439,6,FALSE) -> language | J2: yes | K2: yes | L2: yes | N2: abk | O2: Exact Match | P2: I'm sure | Q2: Arkuashaga | R2: https://search.alexanderstreet.com/preview/work/bibliographic_entity%7Cliner_notes%7C2258560 | S2: Track 8 | T2: Garland Encyclopedia of World Music | U2: No secondary function | V2: No | Z2: There is text in associated ethnography that states what type of song this is (this could be in liner notes, it could be in an email from an anthropologist, etc) | AA2: NA | AB2: Dance song //ON ALEXANDER STREET, IN THE LINER NOTE OF THE ALBUM: The Golden Fleece - Caucasus, Vol. 2: Songs From Abkhazia & Adzharia, PAGE 10// | AC2: NA | AE2: I followed the instructions and I have not yet listened to it! | AF2: Yes | AG2: 6 | AH2: Yes | AJ2: 43259.649 | AK2: AZX
A3: =VLOOKUP(H3,Languages!$A$2:$B$430,2,FALSE) -> Abkhaz-Adyge | B3: Dance | C3: Caucasus | D3: Abkhazia | E3: abkh1244 | F3: abkh1244 | G3: abkh1244 | H3: =VLOOKUP(G3,'languoid 4.0'!$A$1:$I$24439,2,FALSE) -> abkh1242 | I3: =VLOOKUP(G3,'languoid 4.0'!$A$1:$I$24439,6,FALSE) -> language | J3: yes | K3: yes | L3: yes | N3: abk | O3: Exact Match | P3: I'm sure | Q3: Arkushaga | R3: https://search.alexanderstreet.com/preview/work/bibliographic_entity%7Cliner_notes%7C2258560 | S3: Track 23 | T3: Garland Encyclopedia of World Music | U3: No secondary function | V3: No | Z3: There is text in associated ethnography that states what type of song this is (this could be in liner notes, it could be in an email from an anthropologist, etc) | AA3: NA | AB3: Dance melody //ON ALEXANDER STREET, IN THE LINER NOTE OF THE ALBUM: The Golden Fleece - Caucasus, Vol. 2: Songs From Abkhazia & Adzharia, PAGE 11, DESCRIPTION OF SONG 23// | AC3: NA | AD3: Alexander St. lists voice as an instrument but no voice can be heard on recording | AE3: I followed the instructions and I have not yet listened to it! | AF3: No | AG3: 0 | AH3: Yes | AJ3: 43259.684 | AK3: AZX
A4: =VLOOKUP(H4,Languages!$A$2:$B$430,2,FALSE) -> Abkhaz-Adyge | B4: Dance | C4: Central Asia | D4: three different culture groups are represented in the choir who sings the song being Kamancha, chechen, tar | E4: kaba1278 | F4: . | G4: kaba1278 | H4: =VLOOKUP(G4,'languoid 4.0'!$A$1:$I$24439,2,FALSE) -> abkh1242 | I4: =VLOOKUP(G4,'languoid 4.0'!$A$1:$I$24439,6,FALSE) -> language | J4: no | K4: . | L4: . | N4: kbd | O4: Exact Match | P4: I'm sure | Q4: Lezghinka | R4: http://gofile.me/3T2hs/u9J7qpZTJ | S4: Track 2 | T4: Smithsonian Folkways, Before the Revolution | U4: No secondary function | V4: No | Z4: There is text in associated ethnography that states what type of song this is (this could be in liner notes, it could be in an email from an anthropologist, etc) | AA4: Lezghinka //HOLLIS NUMBER 990090350310203941 IN HARVARD ARCHIVE OF WORLD MUSIC HOLLIS RELEVANT TEXT IS IN THE LINEAR NOTES PG. 12// | AB4: Much of the music recorded can be divided into two types; male choirs (tracks 1,3 & 5), and instrumental dance music (tracks 2 &4). //HOLLIS NUMBER 990090350310203941 IN HARVARD ARCHIVE OF WORLD MUSIC HOLLIS RELEVANT TEXT IS IN THE LINEAR NOTES PG. 4// | AC4: NA | AD4: File Path on Synology: /NHS2/submissions/Central Asia/Before the revolution/2 Audio Track.aiff, https://d16klsh1z1xre7-cloudfront-net.ezp-prod1.hul.harvard.edu/dorp/liner/0/cc14/787d/1000089961-liner.pdf | AE4: I followed the instructions and I have not yet listened to it! | AF4: No | AG4: 1 | AH4: Yes | AJ4: 8/19/2018 18:34:37 | AK4: BSG
A5: =VLOOKUP(H5,Languages!$A$2:$B$430,2,FALSE) -> Abkhaz-Adyge | B5: Dance | C5: Central Asia | D5: Kabardian not found of eHARF | E5: kaba1278 | F5: kaba1278 | G5: kaba1278 | H5: =VLOOKUP(G5,'languoid 4.0'!$A$1:$I$24439,2,FALSE) -> abkh1242 | I5: =VLOOKUP(G5,'languoid 4.0'!$A$1:$I$24439,6,FALSE) -> language | J5: yes | K5: yes | L5: yes | N5: kbd | O5: Exact Match | P5: I'm sure | Q5: Lezgihinka | R5: http://gofile.me/3T2hs/MpnkuHTfp | S5: Track 4 | T5: Harvard Archive of World Music HOLLIS | U5: No secondary function | V5: No | Z5: There is text in associated ethnography that states what type of song this is (this could be in liner notes, it could be in an email from an anthropologist, etc) | AA5: Lezgihinka //HOLLIS NUMBER 990090350310203941 IN HARVARD ARCHIVE OF WORLD MUSIC HOLLIS RELEVANT TEXT IS IN THE LINEAR NOTES PG. 12// | AB5: Much of the music recorded can be divided into two types; male choirs (tracks 1,3 & 5), and instrumental dance music (tracks 2 &4). //HOLLIS NUMBER 990090350310203941 IN HARVARD ARCHIVE OF WORLD MUSIC HOLLIS RELEVANT TEXT IS IN THE LINEAR NOTES PG. 4// | AC5: NA | AD5: File Path Synology: /NHS2/submissions/Central Asia/Before the revolution/4 Audio Track.aiff, https://d16klsh1z1xre7-cloudfront-net.ezp-prod1.hul.harvard.edu/dorp/liner/0/cc14/787d/1000089961-liner.pdf | AE5: I followed the instructions and I have not yet listened to it! | AF5: No | AG5: 1 | AH5: Yes | AJ5: 8/19/2018 19:12:57 | AK5: BSG
A6: =VLOOKUP(H6,Languages!$A$2:$B$430,2,FALSE) -> Abkhaz-Adyge | B6: Dance | C6: Central Asia | D6: Kabardian not found of eHARF | E6: kaba1278 | F6: kaba1278 | G6: kaba1278 | H6: =VLOOKUP(G6,'languoid 4.0'!$A$1:$I$24439,2,FALSE) -> abkh1242 | I6: =VLOOKUP(G6,'languoid 4.0'!$A$1:$I$24439,6,FALSE) -> language | J6: yes | K6: yes | L6: yes | N6: kbd | O6: Exact Match | P6: I'm sure | Q6: Lezgihinka | R6: http://gofile.me/3T2hs/MpnkuHTfp | S6: Track 4 | T6: Harvard Archive of World Music HOLLIS | U6: No secondary function | V6: No | Z6: There is text in associated ethnography that states what type of song this is (this could be in liner notes, it could be in an email from an anthropologist, etc) | AA6: Lezgihinka //HOLLIS NUMBER 990090350310203941 IN HARVARD ARCHIVE OF WORLD MUSIC HOLLIS RELEVANT TEXT IS IN THE LINEAR NOTES PG. 12// | AB6: Much of the music recorded can be divided into two types; male choirs (tracks 1,3 & 5), and instrumental dance music (tracks 2 &4). //HOLLIS NUMBER 990090350310203941 IN HARVARD ARCHIVE OF WORLD MUSIC HOLLIS RELEVANT TEXT IS IN THE LINEAR NOTES PG. 4// | AC6: NA | AD6: File Path Synology: /NHS2/submissions/Central Asia/Before the revolution/4 Audio Track.aiff, https://d16klsh1z1xre7-cloudfront-net.ezp-prod1.hul.harvard.edu/dorp/liner/0/cc14/787d/1000089961-liner.pdf | AE6: I followed the instructions and I have not yet listened to it! | AF6: No | AG6: 1 | AH6: Yes | AJ6: 8/19/2018 19:16:46 | AK6: BSG
A7: =VLOOKUP(H7,Languages!$A$2:$B$430,2,FALSE) -> Abkhaz-Adyge | B7: Mourning | C7: Caucasus | D7: Abkhazia | E7: abkh1244 | F7: abkh1244 | G7: abkh1244 | H7: =VLOOKUP(G7,'languoid 4.0'!$A$1:$I$24439,2,FALSE) -> abkh1242 | I7: =VLOOKUP(G7,'languoid 4.0'!$A$1:$I$24439,6,FALSE) -> language | J7: yes | K7: yes | L7: yes | N7: abk | O7: Exact Match | P7: I'm sure | Q7: Azar | R7: https://search.alexanderstreet.com/preview/work/bibliographic_entity%7Cliner_notes%7C2258560 | S7: Track 7 | T7: Garland Encyclopedia of World Music | U7: No secondary function | V7: No | Z7: There is text in associated ethnography that states what type of song this is (this could be in liner notes, it could be in an email from an anthropologist, etc) | AA7: NA | AB7: Funeral lament in memory of a fallen hero //ON ALEXANDER STREET, IN THE LINER NOTE OF THE ALBUM: The Golden Fleece - Caucasus, Vol. 2: Songs From Abkhazia & Adzharia, PAGE 10// | AC7: NA | AE7: I followed the instructions and I have not yet listened to it! | AF7: Yes | AG7: 6 | AH7: Yes | AJ7: 43259.646 | AK7: AZX
A8: =VLOOKUP(H8,Languages!$A$2:$B$430,2,FALSE) -> Abkhaz-Adyge | B8: Mourning | C8: Caucasus | D8: Abkhazia | E8: abkh1244 | F8: abkh1244 | G8: abkh1244 | H8: =VLOOKUP(G8,'languoid 4.0'!$A$1:$I$24439,2,FALSE) -> abkh1242 | I8: =VLOOKUP(G8,'languoid 4.0'!$A$1:$I$24439,6,FALSE) -> language | J8: yes | K8: yes | L8: yes | N8: abk | O8: Exact Match | P8: I'm sure | Q8: Lament | R8: https://search.alexanderstreet.com/preview/work/bibliographic_entity%7Cliner_notes%7C2258560 | S8: Track 11 | T8: Garland Encyclopedia of World Music | U8: Procession - funeral | V8: No | Z8: There is text in associated ethnography that states what type of song this is (this could be in liner notes, it could be in an email from an anthropologist, etc) | AA8: NA | AB8: The keening over the deceased varies in form and melody. It is either loud calls by women of moan singing by men. Sometimes there is musically organized group-keening performed by men, before the funeral starts [11]. //ON ALEXANDER STREET, IN THE LINER NOTE OF THE ALBUM: The Golden Fleece - Caucasus, Vol. 2: Songs From Abkhazia & Adzharia, PAGE 6// | AC8: NA | AE8: I followed the instructions and I have not yet listened to it! | AF8: Yes | AG8: 6 | AH8: Yes | AJ8: 43259.659 | AK8: AZX
A9: =VLOOKUP(H9,Languages!$A$2:$B$430,2,FALSE) -> Abkhaz-Adyge | B9: Praise | C9: Caucasus | D9: Abkhazia | E9: abkh1244 | F9: abkh1244 | G9: abkh1244 | H9: =VLOOKUP(G9,'languoid 4.0'!$A$1:$I$24439,2,FALSE) -> abkh1242 | I9: =VLOOKUP(G9,'languoid 4.0'!$A$1:$I$24439,6,FALSE) -> language | J9: yes | K9: yes | L9: yes | N9: abk | O9: Exact Match | P9: I'm sure | Q9: Hadzhi Kyaranthyku | R9: https://search.alexanderstreet.com/preview/work/bibliographic_entity%7Cliner_notes%7C2258560 | S9: Track 2 | T9: Garland Encyclopedia of World Music | U9: Story | V9: No | Z9: There is text in associated ethnography that states what type of song this is (this could be in liner notes, it could be in an email from an anthropologist, etc) | AA9: NA | AB9: Heroic song about Hadzhi Kyaranthyku //ON ALEXANDER STREET, IN THE LINER NOTE OF THE ALBUM: The Golden Fleece - Caucasus, Vol. 2: Songs From Abkhazia & Adzharia, PAGE 9// | AC9: NA | AE9: I followed the instructions and I have not yet listened to it! | AF9: Yes | AG9: 6 | AH9: Yes | AJ9: 43259.638 | AK9: AZX
A10: =VLOOKUP(H10,Languages!$A$2:$B$430,2,FALSE) -> Abkhaz-Adyge | B10: Praise | C10: Caucasus | D10: Abkhazia | E10: abkh1244 | F10: abkh1244 | G10: abkh1244 | H10: =VLOOKUP(G10,'languoid 4.0'!$A$1:$I$24439,2,FALSE) -> abkh1242 | I10: =VLOOKUP(G10,'languoid 4.0'!$A$1:$I$24439,6,FALSE) -> language | J10: yes | K10: yes | L10: yes | N10: abk | O10: Exact Match | P10: I'm sure | Q10: Chantari Guagua | R10: https://search.alexanderstreet.com/preview/work/bibliographic_entity%7Cliner_notes%7C2258560 | S10: Track 3 | T10: Garland Encyclopedia of World Music | U10: Story | V10: No | Z10: There is text in associated ethnography that states what type of song this is (this could be in liner notes, it could be in an email from an anthropologist, etc) | AA10: NA | AB10: Heroic epic song about Chantari Guagua //ON ALEXANDER STREET, IN THE LINER NOTE OF THE ALBUM: The Golden Fleece - Caucasus, Vol. 2: Songs From Abkhazia & Adzharia, PAGE 9// | AC10: NA | AE10: I followed the instructions and I have not yet listened to it! | AF10: Yes | AG10: 6 | AH10: Yes | AJ10: 43259.64 | AK10: AZX
A11: =VLOOKUP(H11,Languages!$A$2:$B$430,2,FALSE) -> Abkhaz-Adyge | B11: Praise | C11: Caucasus | D11: Abkhazia | E11: abkh1244 | F11: abkh1244 | G11: abkh1244 | H11: =VLOOKUP(G11,'languoid 4.0'!$A$1:$I$24439,2,FALSE) -> abkh1242 | I11: =VLOOKUP(G11,'languoid 4.0'!$A$1:$I$24439,6,FALSE) -> language | J11: yes | K11: yes | L11: yes | N11: abk | O11: Exact Match | P11: I'm sure | Q11: Ozbak | R11: https://search.alexanderstreet.com/preview/work/bibliographic_entity%7Cliner_notes%7C2258560 | S11: Track 17 | T11: Garland Encyclopedia of World Music | U11: No secondary function | V11: No | Z11: There is text in associated ethnography that states what type of song this is (this could be in liner notes, it could be in an email from an anthropologist, etc) | AA11: NA | AB11: In "Ozbak" [17] the only words that come out clearly are: 'Ozbak is our hero', although every singer knows the legend behind the song. Ozbak, according to this legend, managed to overcome grief after his son had been killed. He did not take revenge on those who killed his son, because he believed that his son was to blame. The heroism of the father is in his high sense of justice. The song ends with a dance to praise the hero for his high moral. //ON ALEXANDER STREET, IN THE LINER NOTE OF THE ALBUM: The Golden Fleece - Caucasus, Vol. 2: Songs From Abkhazia & Adzharia, PAGE 7// | AC11: NA | AE11: I followed the instructions and I have not yet listened to it! | AF11: Yes | AG11: 5 | AH11: Yes | AJ11: 43259.67 | AK11: AZX
A12: =VLOOKUP(H12,Languages!$A$2:$B$430,2,FALSE) -> Abkhaz-Adyge | B12: Procession | C12: Caucasus | D12: Abkhazians | E12: abkh1244 | F12: abkh1244 | G12: abkh1244 | H12: =VLOOKUP(G12,'languoid 4.0'!$A$1:$I$24439,2,FALSE) -> abkh1242 | I12: =VLOOKUP(G12,'languoid 4.0'!$A$1:$I$24439,6,FALSE) -> language | J12: yes | K12: yes | L12: yes | N12: abk | O12: Exact Match | P12: I'm sure | Q12: Wedding Song | R12: https://theglobaljukebox.org/?share=Abkhazia-T5413R01 | S12: NA | T12: Global Jukebox | U12: Wedding | V12: No | Z12: The song is identified as such in its title or label | AA12: Genre: Wedding song //CODING ID 4155 IN GLOBAL JUKEBOX// | AB12: NA | AC12: NA | AE12: I followed the instructions and I have not yet listened to it! | AF12: Yes | AG12: 6 | AH12: Yes | AJ12: 43108.783 | AK12: AZX
A13: =VLOOKUP(H13,Languages!$A$2:$B$430,2,FALSE) -> Abkhaz-Adyge | B13: Procession | C13: Caucasus | D13: Abkhazia | E13: abkh1244 | F13: abkh1244 | G13: abkh1244 | H13: =VLOOKUP(G13,'languoid 4.0'!$A$1:$I$24439,2,FALSE) -> abkh1242 | I13: =VLOOKUP(G13,'languoid 4.0'!$A$1:$I$24439,6,FALSE) -> language | J13: yes | K13: yes | L13: yes | N13: abk | O13: Exact Match | P13: I'm sure | Q13: Azar | R13: https://search.alexanderstreet.com/preview/work/bibliographic_entity%7Cliner_notes%7C2258560 | S13: Track 12 | T13: Garland Encyclopedia of World Music | U13: Funeral | V13: No | Z13: There is text in associated ethnography that states what type of song this is (this could be in liner notes, it could be in an email from an anthropologist, etc) | AA13: NA | AB13: Funeral song //ON ALEXANDER STREET, IN THE LINER NOTE OF THE ALBUM: The Golden Fleece - Caucasus, Vol. 2: Songs From Abkhazia & Adzharia, PAGE 11// | AC13: NA | AE13: I followed the instructions and I have not yet listened to it! | AF13: Yes | AG13: 5 | AH13: Yes | AJ13: 43259.651 | AK13: AZX
A14: =VLOOKUP(H14,Languages!$A$2:$B$430,2,FALSE) -> Abkhaz-Adyge | B14: Procession | C14: Caucasus | D14: Abkhazia | E14: abkh1244 | F14: abkh1244 | G14: abkh1244 | H14: =VLOOKUP(G14,'languoid 4.0'!$A$1:$I$24439,2,FALSE) -> abkh1242 | I14: =VLOOKUP(G14,'languoid 4.0'!$A$1:$I$24439,6,FALSE) -> language | J14: yes | K14: yes | L14: yes | N14: abk | O14: Exact Match | P14: I'm sure | Q14: Azar | R14: https://search.alexanderstreet.com/preview/work/bibliographic_entity%7Cliner_notes%7C2258560 | S14: Track 13 | T14: Garland Encyclopedia of World Music | U14: Horse races | V14: No | Z14: There is text in associated ethnography that states what type of song this is (this could be in liner notes, it could be in an email from an anthropologist, etc) | AA14: NA | AB14: 1. Ritual song at the horse races //ON ALEXANDER STREET, IN THE LINER NOTE OF THE ALBUM: The Golden Fleece - Caucasus, Vol. 2: Songs From Abkhazia & Adzharia, PAGE 11// 2. Azar is also the name of a quite different song that is performed before horse races //ON ALEXANDER STREET, IN THE LINER NOTE OF THE ALBUM: The Golden Fleece - Caucasus, Vol. 2: Songs From Abkhazia & Adzharia, PAGE 6// | AC14: NA | AE14: I followed the instructions and I have not yet listened to it! | AF14: Yes | AG14: 5 | AH14: Yes | AJ14: 43259.655 | AK14: AZX
A15: =VLOOKUP(H15,Languages!$A$2:$B$430,2,FALSE) -> Abkhaz-Adyge | B15: Procession | C15: Caucasus | D15: Abkhazia | E15: abkh1244 | F15: abkh1244 | G15: abkh1244 | H15: =VLOOKUP(G15,'languoid 4.0'!$A$1:$I$24439,2,FALSE) -> abkh1242 | I15: =VLOOKUP(G15,'languoid 4.0'!$A$1:$I$24439,6,FALSE) -> language | J15: yes | K15: yes | L15: yes | N15: abk | O15: Exact Match | P15: I'm sure | Q15: Wedding song | R15: https://search.alexanderstreet.com/preview/work/bibliographic_entity%7Cliner_notes%7C2258560 | S15: Track 22 | T15: Garland Encyclopedia of World Music | U15: Wedding | V15: No | Z15: There is text in associated ethnography that states what type of song this is (this could be in liner notes, it could be in an email from an anthropologist, etc) | AA15: Wedding song //ON ALEXANDER STREET, IN THE LINER NOTE OF THE ALBUM: The Golden Fleece - Caucasus, Vol. 2: Songs From Abkhazia & Adzharia, PAGE 11, TITLE OF SONG 22// | AB15: Ritual song melody //ON ALEXANDER STREET, IN THE LINER NOTE OF THE ALBUM: The Golden Fleece - Caucasus, Vol. 2: Songs From Abkhazia & Adzharia, PAGE 11, DESCRIPTION OF SONG 22// | AC15: NA | AE15: I followed the instructions and I have not yet listened to it! | AF15: Yes | AG15: 4 | AH15: Yes | AJ15: 43259.682 | AK15: AZX
A16: =VLOOKUP(H16,Languages!$A$2:$B$430,2,FALSE) -> Abkhaz-Adyge | B16: Story | C16: Caucasus | D16: Abkhazia | E16: abkh1244 | F16: abkh1244 | G16: abkh1244 | H16: =VLOOKUP(G16,'languoid 4.0'!$A$1:$I$24439,2,FALSE) -> abkh1242 | I16: =VLOOKUP(G16,'languoid 4.0'!$A$1:$I$24439,6,FALSE) -> language | J16: yes | K16: yes | L16: yes | N16: abk | O16: Exact Match | P16: I'm sure | Q16: Zhan Achba | R16: https://search.alexanderstreet.com/preview/work/bibliographic_entity%7Cliner_notes%7C2258560 | S16: Track 14 | T16: Garland Encyclopedia of World Music | U16: No secondary function | V16: No | Z16: There is text in associated ethnography that states what type of song this is (this could be in liner notes, it could be in an email from an anthropologist, etc) | AA16: NA | AB16: This is a very special song about a blind singer who was persecuted for his satirical songs. This person did exist in reality. He died in 1916. //ON ALEXANDER STREET, IN THE LINER NOTE OF THE ALBUM: The Golden Fleece - Caucasus, Vol. 2: Songs From Abkhazia & Adzharia, PAGE 6// | AC16: NA | AE16: I followed the instructions and I have not yet listened to it! | AF16: Yes | AG16: 6 | AH16: Yes | AJ16: 43259.663 | AK16: AZX
A17: =VLOOKUP(H17,Languages!$A$2:$B$430,2,FALSE) -> Abkhaz-Adyge | B17: Story | C17: Caucasus | D17: Abkhazia | E17: abkh1244 | F17: abkh1244 | G17: abkh1244 | H17: =VLOOKUP(G17,'languoid 4.0'!$A$1:$I$24439,2,FALSE) -> abkh1242 | I17: =VLOOKUP(G17,'languoid 4.0'!$A$1:$I$24439,6,FALSE) -> language | J17: yes | K17: yes | L17: yes | N17: abk | O17: Exact Match | P17: I'm sure | Q17: Aiba Huita | R17: https://search.alexanderstreet.com/preview/work/bibliographic_entity%7Cliner_notes%7C2258560 | S17: Track 15 | T17: Garland Encyclopedia of World Music | U17: Praise | V17: No | Z17: There is text in associated ethnography that states what type of song this is (this could be in liner notes, it could be in an email from an anthropologist, etc) | AA17: NA | AB17: The song "Aiba Huita" [15] is about the death of a hero who took revenge over the death of this beloved son but perished in this fight. //ON ALEXANDER STREET, IN THE LINER NOTE OF THE ALBUM: The Golden Fleece - Caucasus, Vol. 2: Songs From Abkhazia & Adzharia, PAGE 6// | AC17: NA | AE17: I followed the instructions and I have not yet listened to it! | AF17: Yes | AG17: 6 | AH17: Yes | AJ17: 43259.665 | AK17: AZX
A18: =VLOOKUP(H18,Languages!$A$2:$B$430,2,FALSE) -> Abkhaz-Adyge | B18: Story | C18: Caucasus | D18: Abkhazia | E18: abkh1244 | F18: abkh1244 | G18: abkh1244 | H18: =VLOOKUP(G18,'languoid 4.0'!$A$1:$I$24439,2,FALSE) -> abkh1242 | I18: =VLOOKUP(G18,'languoid 4.0'!$A$1:$I$24439,6,FALSE) -> language | J18: yes | K18: yes | L18: yes | N18: abk | O18: Exact Match | P18: I'm sure | Q18: Narts | R18: https://search.alexanderstreet.com/preview/work/bibliographic_entity%7Cliner_notes%7C2258560 | S18: Track 20 | T18: Garland Encyclopedia of World Music | U18: Praise | V18: No | Z18: There is text in associated ethnography that states what type of song this is (this could be in liner notes, it could be in an email from an anthropologist, etc) | AA18: NA | AB18: The original song about the Narts [20], performed here on achirpan, tells the story: "In old times there lived people, called 'the great Narts'...The heroic deeds of the Narts are still remembered now". //ON ALEXANDER STREET, IN THE LINER NOTE OF THE ALBUM: The Golden Fleece - Caucasus, Vol. 2: Songs From Abkhazia & Adzharia, PAGE 7 & 8// | AC18: NA | AE18: I followed the instructions and I have not yet listened to it! | AF18: Yes | AG18: 2 | AH18: Yes | AJ18: 43259.68 | AK18: AZX
A19: =VLOOKUP(H19,Languages!$A$2:$B$430,2,FALSE) -> Abkhaz-Adyge | B19: Work | C19: Caucasus | D19: Abkhazia | E19: abkh1244 | F19: abkh1244 | G19: abkh1244 | H19: =VLOOKUP(G19,'languoid 4.0'!$A$1:$I$24439,2,FALSE) -> abkh1242 | I19: =VLOOKUP(G19,'languoid 4.0'!$A$1:$I$24439,6,FALSE) -> language | J19: yes | K19: yes | L19: yes | N19: abk | O19: Exact Match | P19: I'm sure | Q19: Auardin | R19: https://search.alexanderstreet.com/preview/work/bibliographic_entity%7Cliner_notes%7C2258560 | S19: Track 5 | T19: Garland Encyclopedia of World Music | U19: No secondary function | V19: No | Z19: There is text in associated ethnography that states what type of song this is (this could be in liner notes, it could be in an email from an anthropologist, etc) | AA19: NA | AB19: Working song //ON ALEXANDER STREET, IN THE LINER NOTE OF THE ALBUM: The Golden Fleece - Caucasus, Vol. 2: Songs From Abkhazia & Adzharia, PAGE 10// | AC19: NA | AE19: I followed the instructions and I have not yet listened to it! | AF19: Yes | AG19: 6 | AH19: Yes | AJ19: 43259.644 | AK19: AZX
A20: =VLOOKUP(H20,Languages!$A$2:$B$430,2,FALSE) -> Afro-Asiatic | B20: Dance | C20: Eastern Africa | D20: Sidama, Sidamo | E20: sida1246 | F20: sida1246 | G20: sida1246 | H20: =VLOOKUP(G20,'languoid 4.0'!$A$1:$I$24439,2,FALSE) -> afro1255 | I20: =VLOOKUP(G20,'languoid 4.0'!$A$1:$I$24439,6,FALSE) -> language | J20: yes | K20: yes | L20: yes | N20: sid | O20: Exact Match | P20: I'm sure | Q20: Maji Dance Music | R20: https://theglobaljukebox.org/?share=Sidama-T5553R13 | S20: NA | T20: Global Jukebox, CREM, Library of Congress | U20: Feast Song | V20: No | Z20: The song is identified as such in its title or label, There is text in associated ethnography that states what type of song this is (this could be in liner notes, it could be in an email from an anthropologist, etc) | AA20: Dance Song //GLOBAL JUKEBOX, CULT: SIDAMA, AUDIO FILE ID T5553R13// | AB20: Dance song; two-part polyphonic music performed at a feast, hocketing, yodel. //GLOBAL JUKEBOX, CODING ID 9428// | AC20: NA | AD20: Global Jukebox-->Wheel-->East Africa/East African Horn/Highland E. Cushites-->Sidama-->Maji Dance Music | AE20: I followed the instructions and I have not yet listened to it! | AF20: Yes | AG20: 6 | AH20: Yes | AJ20: 43222.515 | AK20: ERA
A21: =VLOOKUP(H21,Languages!$A$2:$B$430,2,FALSE) -> Afro-Asiatic | B21: Dance | C21: Eastern Africa | D21: Ajuran | E21: nort3051 | F21: soma1255 | G21: nort3051 | H21: =VLOOKUP(G21,'languoid 4.0'!$A$1:$I$24439,2,FALSE) -> afro1255 | I21: =VLOOKUP(G21,'languoid 4.0'!$A$1:$I$24439,6,FALSE) -> dialect | J21: no | K21: yes | L21: yes | O21: Exact Match | P21: I'm not sure | Q21: Camel Song and Dance | R21: https://theglobaljukebox.org/?share=Ajuran-T5561R03 | S21: NA | T21: Global Jukebox, Library of Congress | U21: Camel song | V21: No | Z21: The song is identified as such in its title or label | AA21: Dance song //GLOBAL JUKEBOX, CODING ID 9975, AUDIO FILE ID T5561R03// | AB21: NA | AC21: NA | AD21: Global Jukebox-->Wheel-->East Africa/East African Horn/Omotic Peoples-->Ajuran-->Camel Song and Dance | AE21: I followed the instructions and I have not yet listened to it! | AF21: Yes | AG21: 5 | AH21: Yes | AJ21: 43222.562 | AK21: ERA
A22: =VLOOKUP(H22,Languages!$A$2:$B$430,2,FALSE) -> Afro-Asiatic | B22: Dance | C22: Eastern Africa | D22: Bederiya (subset of Baggara/Hemat?) | E22: bath1248 | F22: . | G22: suda1236 | H22: =VLOOKUP(G22,'languoid 4.0'!$A$1:$I$24439,2,FALSE) -> afro1255 | I22: =VLOOKUP(G22,'languoid 4.0'!$A$1:$I$24439,6,FALSE) -> language | J22: no | K22: . | L22: . | O22: Exact Match | P22: I'm sure | Q22: Merdum Song | R22: https://theglobaljukebox.org/?share=Bederiya-T5625R09m | S22: NA | T22: Global Jukebox | U22: Dance | V22: No | Z22: There is text in associated ethnography that states what type of song this is (this could be in liner notes, it could be in an email from an anthropologist, etc) | AA22: Merdum Song //GLOBAL JUKEBOX, CODING ID 4211, SONG FIELD// | AB22: Genre: Dance song; Description: Dance with chorus //GLOBAL JUKEBOX, CODING ID 4211// | AC22: NA | AD22: click on green checklist or song title in lower right corner | AE22: Earlier today, I heard maybe a second fading in as it autoplayed after the previous track | AF22: Yes | AG22: 5 | AH22: Yes | AJ22: 4/16/2018 12:22:14 | AK22: MJW
A23: =VLOOKUP(H23,Languages!$A$2:$B$430,2,FALSE) -> Afro-Asiatic | B23: Dance | C23: Northern Africa | D23: Gourara | E23: gour1247 | F23: berb1260 | G23: gour1247 | H23: =VLOOKUP(G23,'languoid 4.0'!$A$1:$I$24439,2,FALSE) -> afro1255 | I23: =VLOOKUP(G23,'languoid 4.0'!$A$1:$I$24439,6,FALSE) -> dialect | J23: no | K23: yes | L23: yes | O23: Exact Match | P23: I'm sure | Q23: Dance with qarqabou | R23: http://www.worldcat.org/oclc/34555452 | S23: Track 7 | T23: NHS 1.0 | V23: No | AA23: 6 | AB23: 6 | AC23: NA | AJ23: 43102.753 | AK23: SDA
A24: =VLOOKUP(H24,Languages!$A$2:$B$430,2,FALSE) -> Afro-Asiatic | B24: Dance | C24: Northern Africa | D24: Atlas Berbers: Shilha / Shluh | E24: cent2194 | F24: berb1260 | G24: cent2194 | H24: =VLOOKUP(G24,'languoid 4.0'!$A$1:$I$24439,2,FALSE) -> afro1255 | I24: =VLOOKUP(G24,'languoid 4.0'!$A$1:$I$24439,6,FALSE) -> language | J24: no | K24: yes | L24: yes | N24: tzm | O24: Exact Match | P24: I'm sure | Q24: Dance Song | R24: http://media.theglobaljukebox.org/audio/T40010R03.mp3 | S24: NA | T24: Global Jukebox | U24: No secondary function | V24: No | Z24: The song is identified as such in its title or label, There is text in associated ethnography that states what type of song this is (this could be in liner notes, it could be in an email from an anthropologist, etc) | AA24: Dance song //GLOBAL JUKEBOX CODING ID 3295 GENRE// | AB24: Male leader in alternation with mixed chorus over bowed lute and percussion //GLOBAL JUKEBOX CODING ID 3295 DESCRIPTION// | AC24: NA | AE24: I followed the instructions and I have not yet listened to it! | AF24: Yes | AG24: 4 | AH24: Yes | AJ24: 4/19/2018 11:12:26 | AK24: MJW
A25: =VLOOKUP(H25,Languages!$A$2:$B$430,2,FALSE) -> Afro-Asiatic | B25: Dance | C25: Northern Africa | D25: Morocco Berbers | E25: cent2194 | F25: riff1234 | G25: cent2194 | H25: =VLOOKUP(G25,'languoid 4.0'!$A$1:$I$24439,2,FALSE) -> afro1255 | I25: =VLOOKUP(G25,'languoid 4.0'!$A$1:$I$24439,6,FALSE) -> language | J25: no | K25: yes | L25: yes | N25: tzm | O25: Exact Match | P25: I'm sure | Q25: Line Dance | R25: http://media.theglobaljukebox.org/audio/T5521R51.mp3 | S25: NA | T25: Global Jukebox | U25: No secondary function | V25: No | Z25: The song is identified as such in its title or label | AA25: Dance song; line dance //GLOBAL JUKEBOX CODING ID 9247 GENRE// | AB25: NA | AC25: NA | AE25: I followed the instructions and I have not yet listened to it! | AF25: Yes | AG25: 4 | AH25: Yes | AJ25: 4/19/2018 11:16:06 | AK25: MJW
A26: =VLOOKUP(H26,Languages!$A$2:$B$430,2,FALSE) -> Afro-Asiatic | B26: Dance | C26: Northern Africa | D26: Tuareg | E26: tuar1240 | F26: tuar1240 | G26: tuar1240 | H26: =VLOOKUP(G26,'languoid 4.0'!$A$1:$I$24439,2,FALSE) -> afro1255 | I26: =VLOOKUP(G26,'languoid 4.0'!$A$1:$I$24439,6,FALSE) -> family | J26: yes | K26: yes | L26: yes | N26: tmh | O26: Most Common Subfamily | P26: I'm sure | Q26: Tohimo Dance | R26: http://media.theglobaljukebox.org/audio/T45022.mp3 | S26: NA | T26: Global Jukebox | U26: No secondary function | V26: No | Z26: The song is identified as such in its title or label | AA26: Dance song //GLOBAL JUKEBOX CODING ID 955 GENRE// | AB26: NA | AC26: NA | AE26: I followed the instructions and I have not yet listened to it! | AF26: Yes | AG26: 4 | AH26: Yes | AJ26: 4/19/2018 11:20:29 | AK26: MJW
A27: =VLOOKUP(H27,Languages!$A$2:$B$430,2,FALSE) -> Afro-Asiatic | B27: Dance | C27: Northern Africa | D27: Tuareg (Morocco Berbers) | E27: hogg1238 | F27: stan1290 | G27: tuar1240 | H27: =VLOOKUP(G27,'languoid 4.0'!$A$1:$I$24439,2,FALSE) -> afro1255 | I27: =VLOOKUP(G27,'languoid 4.0'!$A$1:$I$24439,6,FALSE) -> family | J27: no | K27: no | L27: no | O27: Exact Match | P27: I'm sure | Q27: Suite de ghedras de Goulimine | R27: http://www.worldcat.org/oclc/61711547 | S27: Side B | T27: Global Jukebox, Alan Lomax Collection | U27: Ritual | V27: No | Z27: The song is identified as such in its title or label, There is text in associated ethnography that states what type of song this is (this could be in liner notes, it could be in an email from an anthropologist, etc) | AA27: Ritual song; dance song; religious song; trance song //GLOBAL JUKEBOX CODING ID 9602 GENRE// | AB27: The guedra ritual dance serves as a blessing for friends or married people or to the community, or to submit the self to God; hypnotic and increasingly frenzied dance performed by solo female //GLOBAL JUKEBOX CODING ID 9602 DESCRIPTION// | AC27: NA | AD27: Listed in WorldCat as four tracks: Ghedra douce, Ghedra syncopee, Ghedra endiablee, Ghedra passionnee. | AE27: I followed the instructions and I have not yet listened to it! | AF27: Yes | AG27: 4 | AH27: Yes | AI27: Audio not available on Global Jukebox. | AJ27: 43286.453 | AK27: MJW
A28: =VLOOKUP(H28,Languages!$A$2:$B$430,2,FALSE) -> Afro-Asiatic | B28: Dance | C28: Northern Africa | D28: Atlas Berbers: Shilha/Shluh/Chleuh, Haha tribe | E28: cent2194 | F28: berb1260 | G28: cent2194 | H28: =VLOOKUP(G28,'languoid 4.0'!$A$1:$I$24439,2,FALSE) -> afro1255 | I28: =VLOOKUP(G28,'languoid 4.0'!$A$1:$I$24439,6,FALSE) -> language | J28: no | K28: yes | L28: yes | N28: tzm | O28: Exact Match | P28: I'm sure | Q28: Ahouach of Zaouia | R28: http://media.theglobaljukebox.org/audio/T40010R04.mp3 | S28: NA | T28: Global Jukebox | U28: No secondary function | V28: No | Z28: The song is identified as such in its title or label, There is text in associated ethnography that states what type of song this is (this could be in liner notes, it could be in an email from an anthropologist, etc) | AA28: Dance song; circle dance //GLOBAL JUKEBOX CODING ID 3294 GENRE// | AB28: Ahouach; Circle Dance; from Southern Morocco; men form circle and play bendir drums, while women shuffle in a larger circle around them //GLOBAL JUKEBOX CODING ID 3294 DESCRIPTION// | AC28: NA | AE28: I followed the instructions and I have not yet listened to it! | AF28: Yes | AG28: 5 | AH28: Yes | AJ28: 43286.496 | AK28: MJW
A29: =VLOOKUP(H29,Languages!$A$2:$B$430,2,FALSE) -> Afro-Asiatic | B29: Dance | C29: Northern Africa | D29: Atlas Berbers: Shilha/Shluh/Chleuh, Haha tribe | E29: cent2194 | F29: berb1260 | G29: cent2194 | H29: =VLOOKUP(G29,'languoid 4.0'!$A$1:$I$24439,2,FALSE) -> afro1255 | I29: =VLOOKUP(G29,'languoid 4.0'!$A$1:$I$24439,6,FALSE) -> language | J29: no | K29: yes | L29: yes | N29: tzm | O29: Exact Match | P29: I'm sure | Q29: Ahouach Ded Ida | R29: http://media.theglobaljukebox.org/audio/T40010R01.mp3 | S29: NA | T29: Global Jukebox | U29: No secondary function | V29: No | Z29: The song is identified as such in its title or label, There is text in associated ethnography that states what type of song this is (this could be in liner notes, it could be in an email from an anthropologist, etc) | AA29: Dance song; circle dance //GLOBAL JUKEBOX CODING ID 3297 GENRE// | AB29: Ahouach; Circle Dance; from Southern Morocco; men form circle and play bendir drums, while women shuffle in a larger circle around them //GLOBAL JUKEBOX CODING ID 3297 DESCRIPTION// | AC29: NA | AE29: I followed the instructions and I have not yet listened to it! | AF29: Yes | AG29: 3 | AH29: Yes | AJ29: 43286.499 | AK29: MJW
A30: =VLOOKUP(H30,Languages!$A$2:$B$430,2,FALSE) -> Afro-Asiatic | B30: Dance | C30: Northern Africa | D30: Atlas Berbers: Shilha/Shluh/Chleuh, Haha tribe | E30: cent2194 | F30: berb1260 | G30: cent2194 | H30: =VLOOKUP(G30,'languoid 4.0'!$A$1:$I$24439,2,FALSE) -> afro1255 | I30: =VLOOKUP(G30,'languoid 4.0'!$A$1:$I$24439,6,FALSE) -> language | J30: no | K30: yes | L30: yes | N30: tzm | O30: Exact Match | P30: I'm sure | Q30: Antiphonal song | R30: http://media.theglobaljukebox.org/audio/T40031R02.mp3 | S30: NA | T30: Global Jukebox | U30: No secondary function | V30: No | Z30: The song is identified as such in its title or label, There is text in associated ethnography that states what type of song this is (this could be in liner notes, it could be in an email from an anthropologist, etc) | AA30: Dance song //GLOBAL JUKEBOX CODING ID 3290 GENRE// | AB30: Women dance and sing around the circle of male drummers //GLOBAL JUKEBOX CODING ID 3290 DESCRIPTION// | AC30: NA | AE30: I followed the instructions and I have not yet listened to it! | AF30: Yes | AG30: 4 | AH30: Yes | AJ30: 43286.501 | AK30: MJW
A31: =VLOOKUP(H31,Languages!$A$2:$B$430,2,FALSE) -> Afro-Asiatic | B31: Dance | C31: Northern Africa | D31: Atlas Berbers: Shilha/Shluh/Chleuh, Haha tribe | E31: cent2194 | F31: berb1260 | G31: cent2194 | H31: =VLOOKUP(G31,'languoid 4.0'!$A$1:$I$24439,2,FALSE) -> afro1255 | I31: =VLOOKUP(G31,'languoid 4.0'!$A$1:$I$24439,6,FALSE) -> language | J31: no | K31: yes | L31: yes | N31: tzm | O31: Exact Match | P31: I'm sure | Q31: Great Ahouach of Telouet | R31: http://media.theglobaljukebox.org/audio/T40030R01.mp3 | S31: NA | T31: Global Jukebox | U31: No secondary function | V31: No | Z31: The song is identified as such in its title or label, There is text in associated ethnography that states what type of song this is (this could be in liner notes, it could be in an email from an anthropologist, etc) | AA31: Dance song; festival song //GLOBAL JUKEBOX CODING ID 3293 GENRE// | AB31: Festival dance //GLOBAL JUKEBOX CODING ID 3293 DESCRIPTION// | AC31: NA | AE31: I followed the instructions and I have not yet listened to it! | AF31: Yes | AG31: 4 | AH31: Yes | AJ31: 43286.503 | AK31: MJW
A32: =VLOOKUP(H32,Languages!$A$2:$B$430,2,FALSE) -> Afro-Asiatic | B32: Dance | C32: Northern Africa | D32: Atlas Berbers: Shilha/Shluh/Chleuh, Haha tribe | E32: cent2194 | F32: berb1260 | G32: cent2194 | H32: =VLOOKUP(G32,'languoid 4.0'!$A$1:$I$24439,2,FALSE) -> afro1255 | I32: =VLOOKUP(G32,'languoid 4.0'!$A$1:$I$24439,6,FALSE) -> language | J32: no | K32: yes | L32: yes | N32: tzm | O32: Exact Match | P32: I'm sure | Q32: Ahmeilou | R32: http://www.worldcat.org/oclc/3100954 | S32: Disc 1, Track 1 | T32: Global Jukebox | U32: No secondary function | V32: No | Z32: The song is identified as such in its title or label, There is text in associated ethnography that states what type of song this is (this could be in liner notes, it could be in an email from an anthropologist, etc) | AA32: Dance song //GLOBAL JUKEBOX CODING ID 1588 GENRE// | AB32: //PAGE 2, ITEM 1, IN LIBRARY OF CONGRESS NOTES FOR RECORDING LABORATORY AFS L63 AND L64 https://www.loc.gov/folklife/LP/Morocco_opt.pdf// | AC32: NA | AE32: I followed the instructions and I have not yet listened to it! | AF32: No | AG32: 3 | AH32: Yes | AI32: Global Jukebox uses the title "Prelude and Dance" and does not include audio. | AJ32: 43286.523 | AK32: MJW
A33: =VLOOKUP(H33,Languages!$A$2:$B$430,2,FALSE) -> Afro-Asiatic | B33: Dance | C33: Southeastern Europe | D33: Dervish, Sufi | E33: nucl1301 | F33: arab1395 | G33: arab1395 | H33: =VLOOKUP(G33,'languoid 4.0'!$A$1:$I$24439,2,FALSE) -> afro1255 | I33: =VLOOKUP(G33,'languoid 4.0'!$A$1:$I$24439,6,FALSE) -> family | J33: no | K33: no | L33: no | N33: tur | O33: Exact Match | P33: I'm sure | Q33: Ode by Ahmad al-'Alawi | R33: https://theglobaljukebox.org/?share=Dervish-T5483R23 | S33: Disc 1, Track 5 | T33: Global Jukebox, Smithsonian Folkways | U33: Religious | V33: No | Z33: The song is identified as such in its title or label, There is text in associated ethnography that states what type of song this is (this could be in liner notes, it could be in an email from an anthropologist, etc) | AA33: Religious Song// GLOBAL JUKEBOX, CODING ID 994 // | AB33: Ode by Ahmad Al-'Alawi, opening with the Shahadah, that is the ritual formula La ilaha illa' Llah (d. 1934), repeated here 3 times, Muhammadun rasulu Llah, Islamic Liturgy: Song and Dance at a Meeting of Dervishes. // GLOBAL JUKEBOX, CODING ID 994 // | AC33: NA | AE33: I followed the instructions and I have not yet listened to it! | AF33: Yes | AG33: 6 | AH33: Yes | AJ33: 6/13/2018 18:41:02 | AK33: JCVL
A34: =VLOOKUP(H34,Languages!$A$2:$B$430,2,FALSE) -> Afro-Asiatic | B34: Dance | C34: Southeastern Europe | D34: Dervish, Turkey | E34: nucl1301 | F34: arab1395 | G34: arab1395 | H34: =VLOOKUP(G34,'languoid 4.0'!$A$1:$I$24439,2,FALSE) -> afro1255 | I34: =VLOOKUP(G34,'languoid 4.0'!$A$1:$I$24439,6,FALSE) -> family | J34: no | K34: no | L34: no | N34: tur | O34: Exact Match | P34: I'm sure | Q34: End of the Tarhib/ Invocation of the Divine Name/ The Sacred Dance | R34: https://theglobaljukebox.org/?share=Dervish-T5483R26 | S34: Disc 1, Track 15 | T34: Global Jukebox, Smithsonian Folkways | U34: No secondary function | V34: No | Z34: The song is identified as such in its title or label | AA34: Religious song; Quranic text//GLOBAL JUKEBOX CODING: 997// | AB34: End of the Tarhib (Liturgy), Invocation of the Divine Name, The Sacred Dance, Al-Hadrah (The Presence); words of Blessing upon the Prophet; Quran, XXXIII, v. 23//GLOBAL JUKEBOX CODING: 997// | AC34: NA | AE34: I followed the instructions and I have not yet listened to it! | AF34: Yes | AG34: 6 | AH34: Yes | AJ34: 6/13/2018 20:39:18 | AK34: JCVL
A35: =VLOOKUP(H35,Languages!$A$2:$B$430,2,FALSE) -> Afro-Asiatic | B35: Healing | C35: Central Africa | D35: Kuyu (location: Fort-Rousset, Ouando, Congo) | E35: . | F35: . | G35: nucl1736 | H35: =VLOOKUP(G35,'languoid 4.0'!$A$1:$I$24439,2,FALSE) -> afro1255 | I35: =VLOOKUP(G35,'languoid 4.0'!$A$1:$I$24439,6,FALSE) -> family | J35: . | K35: . | L35: . | N35: #N/A | O35: Unknown | Q35: CHANT DE GUERISON IKANGO | R35: https://archives.crem-cnrs.fr/archives/items/CNRSMH_I_1974_013_004_06/ | S35: Disc 2, Track 14 | T35: CREM | U35: No secondary function | V35: No | Z35: The song is identified as such in its title or label, There is text in associated ethnography that states what type of song this is (this could be in liner notes, it could be in an email from an anthropologist, etc) | AA35: CHANT DE GUERISON IKANGO//CODING ID CNRSMH_I_1974_013_004_06 IN CREM, RELEVANT TEXT IS IN THE TITLE FIELD// | AB35: Guérison//CODING ID CNRSMH_I_1974_013_004_06 IN CREM, RELEVANT TEXT IS IN THE KEYWORDS FIELD// | AC35: NA | AE35: I followed the instructions and I have not yet listened to it! | AF35: Yes | AG35: 3 | AH35: Yes | AJ35: 8/24/2018 14:06:18 | AK35: NCM
A36: =VLOOKUP(H36,Languages!$A$2:$B$430,2,FALSE) -> Afro-Asiatic | B36: Healing | C36: Eastern Africa | D36: Amhara | E36: amha1245 | F36: amha1245 | G36: amha1245 | H36: =VLOOKUP(G36,'languoid 4.0'!$A$1:$I$24439,2,FALSE) -> afro1255 | I36: =VLOOKUP(G36,'languoid 4.0'!$A$1:$I$24439,6,FALSE) -> language | J36: yes | K36: yes | L36: yes | N36: amh | O36: Exact Match | P36: I'm sure | Q36: My Medicine | R36: https://theglobaljukebox.org/?share=Amhara-T5596R07 | S36: NA | T36: Global Jukebox, Library of Congress | U36: No secondary function | V36: No | Z36: The song is identified as such in its title or label | AA36: Healing song //GLOBAL JUKEBOX, CODING ID 3452, AUDIO FILE ID T5596R07// | AB36: NA | AC36: NA | AD36: Global Jukebox-->Wheel-->East Africa/Highland Ethiopia/Ethiopian Semites-->Amhara-->My Medicine | AE36: I followed the instructions and I have not yet listened to it! | AF36: Yes | AG36: 4 | AH36: Yes | AJ36: 43222.57 | AK36: ERA
A37: =VLOOKUP(H37,Languages!$A$2:$B$430,2,FALSE) -> Afro-Asiatic | B37: Healing | C37: Eastern Africa | D37: Amhara | E37: amha1245 | F37: amha1245 | G37: amha1245 | H37: =VLOOKUP(G37,'languoid 4.0'!$A$1:$I$24439,2,FALSE) -> afro1255 | I37: =VLOOKUP(G37,'languoid 4.0'!$A$1:$I$24439,6,FALSE) -> language | J37: yes | K37: yes | L37: yes | N37: amh | O37: Exact Match | P37: I'm sure | Q37: My Medicine 2 | R37: https://theglobaljukebox.org/?share=Amhara-T5596R08 | S37: NA | T37: Global Jukebox | U37: Medicine song | V37: No | Z37: The song is identified as such in its title or label | AA37: Healing Song //GLOBAL JUKEBOX, MY MEDICINE 2, CODING ID 3453, AUDIO FILE ID T5596R08// | AB37: NA | AC37: NA | AD37: Global Jukebox-->Wheel-->East Africa/Highland Ethiopia/Ethiopian Semites-->Amhara-->My Medicine 2 | AE37: I followed the instructions and I have not yet listened to it! | AF37: Yes | AG37: 6 | AH37: Yes | AJ37: 43253.722 | AK37: ERA
A38: =VLOOKUP(H38,Languages!$A$2:$B$430,2,FALSE) -> Afro-Asiatic | B38: Healing | C38: Northern Africa | D38: Tunisians | E38: tuni1260 | F38: stan1318 | G38: tuni1260 | H38: =VLOOKUP(G38,'languoid 4.0'!$A$1:$I$24439,2,FALSE) -> afro1255 | I38: =VLOOKUP(G38,'languoid 4.0'!$A$1:$I$24439,6,FALSE) -> dialect | J38: no | K38: yes | L38: yes | O38: Exact Match | P38: I'm sure | Q38: Sīdī bū ra's el-‘ajmī | R38: http://www.worldcat.org/oclc/758855535 | S38: Track 4 | T38: NHS 1.0 | V38: No | AA38: 20 | AB38: 8-9, 10, 12-15,17-18 | AC38: 10, 14 | AJ38: 43102.76 | AK38: MDS
A39: =VLOOKUP(H39,Languages!$A$2:$B$430,2,FALSE) -> Afro-Asiatic | B39: Healing | C39: Northern Africa | D39: Gnawa | E39: . | F39: arab1395 | G39: arab1395 | H39: =VLOOKUP(G39,'languoid 4.0'!$A$1:$I$24439,2,FALSE) -> afro1255 | I39: =VLOOKUP(G39,'languoid 4.0'!$A$1:$I$24439,6,FALSE) -> family | J39: no | K39: . | L39: . | N39: #N/A | O39: Unknown | Q39: Fatha | R39: http://www.worldcat.org/oclc/25457764 | S39: Side A, Band 3 | T39: WorldCat | U39: No secondary function | V39: No | Z39: There is text in associated ethnography that states what type of song this is (this could be in liner notes, it could be in an email from an anthropologist, etc) | AA39: NA | AB39: The remaining Band 4 [should be 3] contains Fatha, a prayer, since the Gnawas, in addition to providing entertainment through their music and dance on the streets of towns and villages, possess magical power to cure certain diseases and mental disorders. //ETHNOMUSICOLOGY, VOL 19 NO 1, PAGE 155, RECORD REVIEW http://www.jstor.org.ezp-prod1.hul.harvard.edu/stable/849760// | AC39: NA | AH39: No | AJ39: 43409.57 | AK39: MJW
A40: =VLOOKUP(H40,Languages!$A$2:$B$430,2,FALSE) -> Afro-Asiatic | B40: Love | C40: Eastern Africa | D40: Amhara | E40: amha1245 | F40: amha1245 | G40: amha1245 | H40: =VLOOKUP(G40,'languoid 4.0'!$A$1:$I$24439,2,FALSE) -> afro1255 | I40: =VLOOKUP(G40,'languoid 4.0'!$A$1:$I$24439,6,FALSE) -> language | J40: yes | K40: yes | L40: yes | N40: amh | O40: Exact Match | P40: I'm sure | Q40: Shemonmuanaye | R40: http://www.worldcat.org/oclc/2135349 | S40: Side 2, Track 1 | T40: NHS 1.0 | V40: No | AA40: 7 | AB40: 7 | AC40: NA | AJ40: 43102.764 | AK40: CMB
A41: =VLOOKUP(H41,Languages!$A$2:$B$430,2,FALSE) -> Afro-Asiatic | B41: Love | C41: Eastern Africa | D41: Gidole, Gardulla | E41: dira1242 | F41: dira1242 | G41: dira1242 | H41: =VLOOKUP(G41,'languoid 4.0'!$A$1:$I$24439,2,FALSE) -> afro1255 | I41: =VLOOKUP(G41,'languoid 4.0'!$A$1:$I$24439,6,FALSE) -> language | J41: yes | K41: yes | L41: yes | N41: gdl | O41: Exact Match | P41: I'm sure | Q41: Love Song | R41: https://theglobaljukebox.org/?share=Gidole-T5553R04 | S41: NA | T41: Global Jukebox, CREM, Library of Congress | U41: No secondary function | V41: No | Z41: The song is identified as such in its title or label | AA41: Love Song //GLOBAL JUKEBOX, CODING ID 9421, AUDIO FILE ID T5553R04// | AB41: NA | AC41: NA | AD41: Global Jukebox-->Wheel-->East Africa/Kenya/Ethiopia/Oromo Cushites-->Gidole-->Love Song | AE41: I followed the instructions and I have not yet listened to it! | AF41: Yes | AG41: 6 | AH41: Yes | AJ41: 43222.532 | AK41: ERA
A42: =VLOOKUP(H42,Languages!$A$2:$B$430,2,FALSE) -> Afro-Asiatic | B42: Love | C42: Eastern Africa | D42: Somalis, Soomaali | E42: nort3051 | F42: soma1255 | G42: nort3051 | H42: =VLOOKUP(G42,'languoid 4.0'!$A$1:$I$24439,2,FALSE) -> afro1255 | I42: =VLOOKUP(G42,'languoid 4.0'!$A$1:$I$24439,6,FALSE) -> dialect | J42: no | K42: yes | L42: yes | O42: Exact Match | P42: I'm sure | Q42: Love song | R42: https://theglobaljukebox.org/?share=Somalis-T5566R23 | S42: NA | T42: Global Jukebox, Library of Congress | U42: Song for royalty | V42: No | Z42: The song is identified as such in its title or label | AA42: Love song //GLOBAL JUKEBOX, CODING ID 4454, AUDIO FILE ID T5566R23// | AB42: Love song; woman singing strophic love song during Haile Selassie's birthday celebration, July 23, 1972 //GLOBAL JUKEBOX, CODING ID 4454, AUDIO FILE ID T5566R23// | AC42: NA | AD42: Global Jukebox-->Wheel-->East Africa/East African Horn/Lowland E.Cushites-->Somalis-->Love song | AE42: I followed the instructions and I have not yet listened to it! | AF42: Yes | AG42: 5 | AH42: Yes | AJ42: 43222.544 | AK42: ERA
A43: =VLOOKUP(H43,Languages!$A$2:$B$430,2,FALSE) -> Afro-Asiatic | B43: Love | C43: Eastern Africa | D43: Afar | E43: afar1241 | F43: afar1241 | G43: afar1241 | H43: =VLOOKUP(G43,'languoid 4.0'!$A$1:$I$24439,2,FALSE) -> afro1255 | I43: =VLOOKUP(G43,'languoid 4.0'!$A$1:$I$24439,6,FALSE) -> language | J43: yes | K43: yes | L43: yes | N43: aar | O43: Most Common Subfamily | P43: I'm sure | Q43: Love Song | R43: http://media.theglobaljukebox.org/audio/T40026R04m.mp3 | S43: NA | T43: Global Jukebox | U43: Song for royalty | V43: No | Z43: The song is identified as such in its title or label | AA43: Love song //GLOBAL JUKEBOX, CODING ID 2049, AUDIO FILE ID T40026R04m// | AB43: NA | AC43: NA | AD43: Global Jukebox-->Wheel-->East Africa / East African Horn / Lowland E. Cushites-->Afar-->Love Song | AE43: I followed the instructions and I have not yet listened to it! | AF43: Yes | AG43: 5 | AH43: Yes | AJ43: 43314.598 | AK43: ERA
A44: =VLOOKUP(H44,Languages!$A$2:$B$430,2,FALSE) -> Afro-Asiatic | B44: Love | C44: Eastern Africa | D44: Amhara | E44: amha1245 | F44: amha1245 | G44: amha1245 | H44: =VLOOKUP(G44,'languoid 4.0'!$A$1:$I$24439,2,FALSE) -> afro1255 | I44: =VLOOKUP(G44,'languoid 4.0'!$A$1:$I$24439,6,FALSE) -> language | J44: yes | K44: yes | L44: yes | N44: amh | O44: Exact Match | P44: I'm sure | Q44: Love Song | R44: http://media.theglobaljukebox.org/audio/T40019R07.mp3 | S44: NA | T44: Global Jukebox, Ayele Abebe, Ethiopia I. Music from Ethiopia | U44: No secondary function | V44: No | Z44: The song is identified as such in its title or label, There is text in associated ethnography that states what type of song this is (this could be in liner notes, it could be in an email from an anthropologist, etc) | AA44: Love Song //GLOBAL JUKEBOX, CODING ID 1853, AUDIO FILE ID T40019R07// | AB44: Traditional love song with slightly modernized words //GLOBAL JUKEBOX, CODING ID 1853, AUDIO FILE ID T40019R07// | AC44: NA | AD44: Global Jukebox-->Wheel-->Amhara-->Love Song (Coding ID 1853) | AE44: I followed the instructions and I have not yet listened to it! | AF44: Yes | AG44: 5 | AH44: Yes | AI44: There are a couple of 'Love Song' titles in the Amhara culture, take note of coding ID. | AJ44: 2/14/2018 14:20:34 | AK44: ERA
A45: =VLOOKUP(H45,Languages!$A$2:$B$430,2,FALSE) -> Afro-Asiatic | B45: Love | C45: Eastern Africa | D45: Baggara / Hemat | E45: bath1248 | F45: arab1395 | G45: bath1248 | H45: =VLOOKUP(G45,'languoid 4.0'!$A$1:$I$24439,2,FALSE) -> afro1255 | I45: =VLOOKUP(G45,'languoid 4.0'!$A$1:$I$24439,6,FALSE) -> dialect | J45: no | K45: yes | L45: yes | O45: Exact Match | P45: I'm sure | Q45: Song for Her Lover | R45: https://theglobaljukebox.org/?share=Baggara-T5626R18m | S45: NA | T45: Global Jukebox | U45: No secondary function | V45: No | Z45: The song is identified as such in its title or label | AA45: Song for Her Lover //GLOBAL JUKEBOX, CODING ID 4204: SONG, GENRE, DESCRIPTION// | AB45: NA | AC45: NA | AD45: Click on the green checklist or song title for metadata | AE45: I followed the instructions and I have not yet listened to it! | AF45: Yes | AG45: 5 | AH45: Yes | AJ45: 4/16/2018 12:15:39 | AK45: MJW
A46: =VLOOKUP(H46,Languages!$A$2:$B$430,2,FALSE) -> Afro-Asiatic | B46: Love | C46: Middle East | D46: Druze | E46: sunn1238 | F46: arab1395 | G46: leva1239 | H46: =VLOOKUP(G46,'languoid 4.0'!$A$1:$I$24439,2,FALSE) -> afro1255 | I46: =VLOOKUP(G46,'languoid 4.0'!$A$1:$I$24439,6,FALSE) -> family | J46: no | K46: yes | L46: yes | O46: Exact Match | P46: I'm sure | Q46: Love song | R46: http://media.theglobaljukebox.org/audio/T5484R19.mp3 | S46: NA | T46: Global Jukebox | U46: No secondary function | V46: No | Z46: The song is identified as such in its title or label | AA46: Love song // CODING ID 1479 IN GLOBAL JUKEBOX, RELEVANT TEXT IS IN THE DESCRIPTION FIELD//) | AB46: NA | AC46: NA | AE46: I followed the instructions and I have not yet listened to it! | AF46: Yes | AG46: 6 | AH46: Yes | AJ46: 43318.621 | AK46: SHJ
A47: =VLOOKUP(H47,Languages!$A$2:$B$430,2,FALSE) -> Afro-Asiatic | B47: Love | C47: Middle East | D47: Kathiri Bedouin | E47: arab1395 | F47: arab1395 | G47: arab1393 | H47: =VLOOKUP(G47,'languoid 4.0'!$A$1:$I$24439,2,FALSE) -> afro1255 | I47: =VLOOKUP(G47,'languoid 4.0'!$A$1:$I$24439,6,FALSE) -> family | J47: yes | K47: yes | L47: yes | O47: Exact Match | P47: I'm sure | Q47: Love Song | R47: http://media.theglobaljukebox.org/audio/T5482R02.mp3 | S47: NA | T47: Global Jukebox, Smithsonian Folkways | U47: No secondary function | V47: No | Z47: The song is identified as such in its title or label, The lyrics made it clear to me what type of song this is | AA47: Love song // CODING ID 3623 IN GLOBAL JUKEBOX, RELEVANT TEXT IS IN THE DESCRIPTION FIELD// | AB47: NA | AC47: Description: Lyrics: Why, oh gardener, are you awake and not asleep? And you prevent me from coming to my beloved // CODING ID 3623 IN GLOBAL JUKEBOX // | AE47: I followed the instructions and I have not yet listened to it! | AF47: Yes | AG47: 6 | AH47: Yes | AJ47: 43318.68 | AK47: SHJ
A48: =VLOOKUP(H48,Languages!$A$2:$B$430,2,FALSE) -> Afro-Asiatic | B48: Love | C48: Middle East | D48: Yemenite Jews | E48: jude1267 | F48: arab1395 | G48: jude1267 | H48: =VLOOKUP(G48,'languoid 4.0'!$A$1:$I$24439,2,FALSE) -> afro1255 | I48: =VLOOKUP(G48,'languoid 4.0'!$A$1:$I$24439,6,FALSE) -> language | J48: no | K48: yes | L48: yes | N48: jye | O48: Exact Match | P48: I'm sure | Q48: Love Song | R48: http://media.theglobaljukebox.org/audio/T5482R04.mp3 | S48: NA | T48: Global Jukebox, Smithsonian Folkways | U48: No secondary function | V48: No | Z48: The song is identified as such in its title or label | AA48: Love Song // CODING ID 716 IN GLOBAL JUKEBOX, RELEVANT TEXT IS IN THE DESCRIPTION FIELD// | AB48: NA | AC48: NA | AE48: I followed the instructions and I have not yet listened to it! | AF48: Yes | AG48: 3 | AH48: Yes | AJ48: 43318.716 | AK48: SHJ
A49: =VLOOKUP(H49,Languages!$A$2:$B$430,2,FALSE) -> Afro-Asiatic | B49: Love | C49: Northern Africa | D49: Tuareg | E49: tuar1240 | F49: tuar1240 | G49: tuar1240 | H49: =VLOOKUP(G49,'languoid 4.0'!$A$1:$I$24439,2,FALSE) -> afro1255 | I49: =VLOOKUP(G49,'languoid 4.0'!$A$1:$I$24439,6,FALSE) -> family | J49: yes | K49: yes | L49: yes | N49: tmh | O49: Most Common Subfamily | P49: I'm sure | Q49: Ezzel n oufada aoua etteb ales ou n abaradh | R49: http://www.worldcat.org/oclc/2270693 | S49: Side 1, Track 3 | T49: NHS 1.0 | V49: No | AA49: 6 | AB49: 43652 | AC49: NA | AJ49: 43102.727 | AK49: SDA
A50: =VLOOKUP(H50,Languages!$A$2:$B$430,2,FALSE) -> Afro-Asiatic | B50: Love | C50: Northern Africa | D50: Algerian Gourara Tuareg | E50: taha1241 | F50: taha1241 | G50: taha1241 | H50: =VLOOKUP(G50,'languoid 4.0'!$A$1:$I$24439,2,FALSE) -> afro1255 | I50: =VLOOKUP(G50,'languoid 4.0'!$A$1:$I$24439,6,FALSE) -> language | J50: yes | K50: yes | L50: yes | N50: thv | O50: Exact Match | P50: I'm sure | Q50: Tagerrabt; Ya salat 'alik | R50: http://media.theglobaljukebox.org/audio/T5581R02.mp3 | S50: NA | T50: Global Jukebox | U50: Ceremonial song | V50: No | Z50: There is text in associated ethnography that states what type of song this is (this could be in liner notes, it could be in an email from an anthropologist, etc), The lyrics made it clear to me what type of song this is | AA50: Ceremonial song; women's song //GLOBAL JUKEBOX CODING ID 9927 GENRE// | AB50: We Bow to You; family ceremonial song sung by women; regional lyrics combining amorous ecstasy and religious fervor: [lyrics follow] //GLOBAL JUKEBOX CODING ID 9927 DESCRIPTION// | AC50: Maidens, you are vases for perfume, you are music and camphor which scent those who use it/Tell him: I too love you but I cannot get to you because of all your guardians //GLOBAL JUKEBOX CODING ID 9927 DESCRIPTION// | AE50: I followed the instructions and I have not yet listened to it! | AF50: Yes | AG50: 6 | AH50: Yes | AI50: [this observation made after listening to the song] the description says that it is sung by women, but it sounds like men are singing | AJ50: 4/20/2018 12:42:48 | AK50: MJW
A51: =VLOOKUP(H51,Languages!$A$2:$B$430,2,FALSE) -> Afro-Asiatic | B51: Love | C51: Northern Africa | D51: Tuareg | E51: tuar1240 | F51: tuar1240 | G51: tuar1240 | H51: =VLOOKUP(G51,'languoid 4.0'!$A$1:$I$24439,2,FALSE) -> afro1255 | I51: =VLOOKUP(G51,'languoid 4.0'!$A$1:$I$24439,6,FALSE) -> family | J51: yes | K51: yes | L51: yes | N51: tmh | O51: Most Common Subfamily | P51: I'm sure | Q51: Chikishikishin | R51: http://media.theglobaljukebox.org/audio/T5523R22.mp3 | S51: NA | T51: Global Jukebox | U51: No secondary function | V51: No | Z51: The song is identified as such in its title or label, There is text in associated ethnography that states what type of song this is (this could be in liner notes, it could be in an email from an anthropologist, etc) | AA51: Love song //GLOBAL JUKEBOX CODING ID 954 GENRE// | AB51: An ahal, or love song, by a man accompanied by on the imzhad, one string violin //GLOBAL JUKEBOX CODING ID 954 DESCRIPTION// | AC51: NA | AE51: I followed the instructions and I have not yet listened to it! | AF51: Yes | AG51: 5 | AH51: Yes | AJ51: 4/20/2018 12:46:08 | AK51: MJW
A52: =VLOOKUP(H52,Languages!$A$2:$B$430,2,FALSE) -> Afro-Asiatic | B52: Love | C52: Northern Africa | D52: Tuareg | E52: tuar1240 | F52: tuar1240 | G52: tuar1240 | H52: =VLOOKUP(G52,'languoid 4.0'!$A$1:$I$24439,2,FALSE) -> afro1255 | I52: =VLOOKUP(G52,'languoid 4.0'!$A$1:$I$24439,6,FALSE) -> family | J52: yes | K52: yes | L52: yes | N52: tmh | O52: Most Common Subfamily | P52: I'm sure | Q52: Tailaff | R52: http://media.theglobaljukebox.org/audio/T9525R32.mp3 | S52: NA | T52: Global Jukebox | U52: No secondary function | V52: No | Z52: The song is identified as such in its title or label, There is text in associated ethnography that states what type of song this is (this could be in liner notes, it could be in an email from an anthropologist, etc) | AA52: Love song //GLOBAL JUKEBOX CODING ID 9387 GENRE// | AB52: Love song by a male soloist accompanied by a virtuosic female Inzad (one string fiddle) player //GLOBAL JUKEBOX CODING ID 9387 DESCRIPTION// | AC52: NA | AE52: I followed the instructions and I have not yet listened to it! | AF52: Yes | AG52: 5 | AH52: Yes | AJ52: 4/20/2018 12:48:31 | AK52: MJW
A53: =VLOOKUP(H53,Languages!$A$2:$B$430,2,FALSE) -> Afro-Asiatic | B53: Love | C53: Northern Africa | D53: Egypt | E53: egyp1253 | F53: arab1395 | G53: egyp1253 | H53: =VLOOKUP(G53,'languoid 4.0'!$A$1:$I$24439,2,FALSE) -> afro1255 | I53: =VLOOKUP(G53,'languoid 4.0'!$A$1:$I$24439,6,FALSE) -> language | J53: no | K53: yes | L53: yes | N53: arz | O53: Exact Match | P53: I'm sure | Q53: Love Song | R53: http://media.theglobaljukebox.org/audio/T5543R13.mp3 | S53: NA | T53: Global Jukebox | U53: No secondary function | V53: No | Z53: The song is identified as such in its title or label | AA53: Love song //GLOBAL JUKEBOX CODING ID 3239 GENRE// | AB53: NA | AC53: NA | AE53: I followed the instructions and I have not yet listened to it! | AF53: Yes | AG53: 3 | AH53: Yes | AJ53: 43317.706 | AK53: MJW
A54: =VLOOKUP(H54,Languages!$A$2:$B$430,2,FALSE) -> Afro-Asiatic | B54: Love | C54: Northern Africa | D54: Tunisia | E54: tuni1260 | F54: arab1395 | G54: tuni1260 | H54: =VLOOKUP(G54,'languoid 4.0'!$A$1:$I$24439,2,FALSE) -> afro1255 | I54: =VLOOKUP(G54,'languoid 4.0'!$A$1:$I$24439,6,FALSE) -> dialect | J54: no | K54: yes | L54: yes | O54: Exact Match | P54: I'm sure | Q54: Love Song | R54: http://media.theglobaljukebox.org/audio/T5522R98.mp3 | S54: NA | T54: Global Jukebox | U54: No secondary function | V54: No | Z54: The song is identified as such in its title or label | AA54: Burjîla; love song; lyric song //GLOBAL JUKEBOX CODING ID 4127 GENRE// | AB54: NA | AC54: NA | AE54: I followed the instructions and I have not yet listened to it! | AF54: Yes | AG54: 6 | AH54: Yes | AJ54: 43317.708 | AK54: MJW
A55: =VLOOKUP(H55,Languages!$A$2:$B$430,2,FALSE) -> Afro-Asiatic | B55: Love | C55: Northern Africa | D55: Tunisia | E55: tuni1260 | F55: arab1395 | G55: tuni1260 | H55: =VLOOKUP(G55,'languoid 4.0'!$A$1:$I$24439,2,FALSE) -> afro1255 | I55: =VLOOKUP(G55,'languoid 4.0'!$A$1:$I$24439,6,FALSE) -> dialect | J55: no | K55: yes | L55: yes | O55: Exact Match | P55: I'm sure | Q55: Song of the Salhi type | R55: http://media.theglobaljukebox.org/audio/T45043.mp3 | S55: NA | T55: Global Jukebox | U55: No secondary function | V55: No | Z55: The song is identified as such in its title or label, There is text in associated ethnography that states what type of song this is (this could be in liner notes, it could be in an email from an anthropologist, etc) | AA55: Salhi; love song; lament //GLOBAL JUKEBOX CODING ID 4261 GENRE// | AB55: Love song; Salhi song sung with lamenting strains full of trembling and quivering tones //GLOBAL JUKEBOX CODING ID 4261 DESCRIPTION// | AC55: NA | AE55: I followed the instructions and I have not yet listened to it! | AF55: Yes | AG55: 5 | AH55: Yes | AJ55: 43317.71 | AK55: MJW
A56: =VLOOKUP(H56,Languages!$A$2:$B$430,2,FALSE) -> Afro-Asiatic | B56: Love | C56: Northern Africa | D56: Sahrawi: Hassaniya | E56: hass1238 | F56: arab1395 | G56: hass1238 | H56: =VLOOKUP(G56,'languoid 4.0'!$A$1:$I$24439,2,FALSE) -> afro1255 | I56: =VLOOKUP(G56,'languoid 4.0'!$A$1:$I$24439,6,FALSE) -> language | J56: no | K56: yes | L56: yes | N56: mey | O56: Exact Match | P56: I'm sure | Q56: I have to visit Bamuera | R56: https://sounds.bl.uk/World-and-traditional-music/Violeta-Ruano-portraits-of-Saharawi-Music/025M-C1640X0079XX-0001V0 | S56: NA | T56: British Library | U56: No secondary function | V56: No | Z56: There is text in associated ethnography that states what type of song this is (this could be in liner notes, it could be in an email from an anthropologist, etc) | AA56: Love songs //BRITISH LIBRARY VIOLETA RUANO PORTRAITS OF SAHARAWI MUSIC GENRE// | AB56: This song is a traditional tune from the repertoire of the lashuar, very short, communal songs that used to be played at family gatherings. It talks about a beduin region in Mauritania named Bamuera. The poet loves a woman from the region and writes about his feelings. The performance occasion was a private session at the cultural centre of Ausserd camp. Mariem Mouloud, expert in traditional music, was playing the traditional tbal drum. Traditional Saharawi music was always played with only voice and drum. It's very quiet music, to be able to listen to the words. //BRITISH LIBRARY, SHELF MARK C1640/79, VIOLETA RUANO PORTRAITS OF SAHARAWI MUSIC, I HAVE TO VISIT BAMUERA, ABSTRACT// | AC56: NA | AE56: I followed the instructions and I have not yet listened to it! | AF56: Yes | AG56: 6 | AH56: Yes | AJ56: 43317.736 | AK56: MJW
A57: =VLOOKUP(H57,Languages!$A$2:$B$430,2,FALSE) -> Afro-Asiatic | B57: Love | C57: Northern Africa | D57: Sahrawi: Hassaniya | E57: hass1238 | F57: arab1395 | G57: hass1238 | H57: =VLOOKUP(G57,'languoid 4.0'!$A$1:$I$24439,2,FALSE) -> afro1255 | I57: =VLOOKUP(G57,'languoid 4.0'!$A$1:$I$24439,6,FALSE) -> language | J57: no | K57: yes | L57: yes | N57: mey | O57: Exact Match | P57: I'm sure | Q57: Bib's daughter | R57: https://sounds.bl.uk/World-and-traditional-music/Violeta-Ruano-portraits-of-Saharawi-Music/025M-C1640X0076XX-0001V0 | S57: NA | T57: British Library | U57: No secondary function | V57: No | Z57: The song is identified as such in its title or label, There is text in associated ethnography that states what type of song this is (this could be in liner notes, it could be in an email from an anthropologist, etc) | AA57: Love songs //BRITISH LIBRARY, VIOLETA RUANO PORTRAITS OF SAHARAWI MUSIC, GENRE// | AB57: This song is a modern interpretation of a traditional love song from the repertoire of the lashuar, very short, communal songs that used to be played at family gatherings. In it, a man expresses his feelings for a woman.The performance occasion was a rehearsal of the government musicians of the Ausserd camp. The recording was made in the cultural centre, where there were a lot of people coming in and out. The band structure voice, electric guitar and electronic keyboard is the most common one for the performance of Saharawi music nowadays. The singer was playing the traditional tbal drum. //BRITISH LIBRARY, SHELF MARK C1640/76, VIOLETA RUANO PORTRAITS OF SAHARAWI MUSIC, BIB'S DAUGHTER, ABSTRACT// | AC57: NA | AE57: I followed the instructions and I have not yet listened to it! | AF57: Yes | AG57: 4 | AH57: Yes | AJ57: 43348.472 | AK57: MJW
A58: =VLOOKUP(H58,Languages!$A$2:$B$430,2,FALSE) -> Afro-Asiatic | B58: Lullaby | C58: Northern Africa | D58: Tuareg | E58: tuar1240 | F58: tuar1240 | G58: tuar1240 | H58: =VLOOKUP(G58,'languoid 4.0'!$A$1:$I$24439,2,FALSE) -> afro1255 | I58: =VLOOKUP(G58,'languoid 4.0'!$A$1:$I$24439,6,FALSE) -> family | J58: yes | K58: yes | L58: yes | N58: tmh | O58: Most Common Subfamily | P58: I'm sure | Q58: Lullaby | R58: http://www.worldcat.org/oclc/698168574 | S58: Track 6, Song 3 | T58: NHS 1.0 | V58: No | AA58: 8 | AB58: 8 | AC58: 8 | AJ58: 43102.748 | AK58: MDS
A59: =VLOOKUP(H59,Languages!$A$2:$B$430,2,FALSE) -> Afro-Asiatic | B59: Lullaby | C59: Northern Africa | D59: Tuareg | E59: tuar1240 | F59: tuar1240 | G59: tuar1240 | H59: =VLOOKUP(G59,'languoid 4.0'!$A$1:$I$24439,2,FALSE) -> afro1255 | I59: =VLOOKUP(G59,'languoid 4.0'!$A$1:$I$24439,6,FALSE) -> family | J59: yes | K59: yes | L59: yes | N59: tmh | O59: Most Common Subfamily | P59: I'm sure | Q59: Beraceuse | R59: https://theglobaljukebox.org/?share=Tuareg-T5596R01 | S59: NA | T59: Global Jukebox | U59: No secondary function | V59: No | Z59: The song is identified as such in its title or label | AA59: Lullaby | AB59: Lullaby; fragments from a female soloist; repetition of phrases gives chant-like litany | AC59: NA | AE59: I followed the instructions and I have not yet listened to it! | AF59: Yes | AG59: 5 | AH59: Yes | AJ59: 7/15/2018 14:49:41 | AK59: RJW
A60: =VLOOKUP(H60,Languages!$A$2:$B$430,2,FALSE) -> Afro-Asiatic | B60: Lullaby | C60: Western Africa | D60: Tuareg | E60: tama1365 | F60: tama1365 | G60: tama1365 | H60: =VLOOKUP(G60,'languoid 4.0'!$A$1:$I$24439,2,FALSE) -> afro1255 | I60: =VLOOKUP(G60,'languoid 4.0'!$A$1:$I$24439,6,FALSE) -> language | J60: yes | K60: yes | L60: yes | N60: taq | O60: Exact Match | P60: I'm sure | Q60: “Herding Song, Marriage Song, Lullaby” | R60: https://folkways.si.edu/herding-song-marriage-song-lullaby/islamica-world/music/track/smithsonian | S60: Disc 1, Track 6 | T60: Smithsonian Folkways | U60: Marriage Song, Herding Song | V60: No | Z60: The song is identified as such in its title or label | AA60: “Herding Song, Marriage Song, Lullaby”//SMITHSONIAN FOLKWAYS CATALOGUE NUMBER FW08852_106 | AB60: NA | AC60: NA | AE60: I followed the instructions and I have not yet listened to it! | AF60: Yes | AG60: 6 | AH60: Yes | AJ60: 7/20/2018 19:54:51 | AK60: JMI
A61: =VLOOKUP(H61,Languages!$A$2:$B$430,2,FALSE) -> Afro-Asiatic | B61: Mourning | C61: Middle East | D61: Druze | E61: sunn1238 | F61: arab1395 | G61: leva1239 | H61: =VLOOKUP(G61,'languoid 4.0'!$A$1:$I$24439,2,FALSE) -> afro1255 | I61: =VLOOKUP(G61,'languoid 4.0'!$A$1:$I$24439,6,FALSE) -> family | J61: no | K61: yes | L61: yes | O61: Exact Match | P61: I'm sure | Q61: Haddada | R61: http://media.theglobaljukebox.org/audio/T5521R54.mp3 | S61: NA | T61: Global Jukebox | U61: No secondary function | V61: No | Z61: There is text in associated ethnography that states what type of song this is (this could be in liner notes, it could be in an email from an anthropologist, etc) | AA61: Haddada // CODING ID 9245 IN GLOBAL JUKEBOX, RELEVANT TEXT IS IN THE DESCRIPTION FIELD // | AB61: Genre: Funeral song, Description: Song of eulogy in antiphony // CODING ID 9245 IN GLOBAL JUKEBOX // | AC61: NA | AE61: I followed the instructions and I have not yet listened to it! | AF61: Yes | AG61: 6 | AH61: Yes | AJ61: 43318.626 | AK61: SHJ
A62: =VLOOKUP(H62,Languages!$A$2:$B$430,2,FALSE) -> Afro-Asiatic | B62: Mourning | C62: Middle East | D62: Kathiri Bedouin | E62: arab1395 | F62: arab1395 | G62: arab1393 | H62: =VLOOKUP(G62,'languoid 4.0'!$A$1:$I$24439,2,FALSE) -> afro1255 | I62: =VLOOKUP(G62,'languoid 4.0'!$A$1:$I$24439,6,FALSE) -> family | J62: yes | K62: yes | L62: yes | O62: Exact Match | P62: I'm sure | Q62: Song of Grieving | R62: http://media.theglobaljukebox.org/audio/T5482R07.mp3 | S62: NA | T62: Global Jukebox | U62: No secondary function | V62: No | Z62: The song is identified as such in its title or label | AA62: Song of Grieving, Genre: Mourning song // CODING ID 3627 IN GLOBAL JUKEBOX // | AB62: NA | AC62: NA | AE62: I followed the instructions and I have not yet listened to it! | AF62: Yes | AG62: 6 | AH62: Yes | AJ62: 43318.683 | AK62: SHJ
A63: =VLOOKUP(H63,Languages!$A$2:$B$430,2,FALSE) -> Afro-Asiatic | B63: Mourning | C63: Middle East | D63: Druze | E63: arab1395 | F63: arab1395 | G63: leva1239 | H63: =VLOOKUP(G63,'languoid 4.0'!$A$1:$I$24439,2,FALSE) -> afro1255 | I63: =VLOOKUP(G63,'languoid 4.0'!$A$1:$I$24439,6,FALSE) -> family | J63: yes | K63: yes | L63: yes | O63: Exact Match | P63: I'm sure | Q63: Hida Song for a Deceased Young Man | R63: https://folkways.si.edu/salman-al-arfush/ida-song-for-a-deceased-young-man/islamica-world/music/track/smithsonian | S63: Disc 1, Track 2 | T63: Smithsonian Folkways | U63: No secondary function | V63: No | Z63: The song is identified as such in its title or label | AA63: Hida Song for a Deceased Young Man //SMITHSONIAN FOLKWAYS CATALOGUE NUMBER: FW04046_102// | AB63: NA | AC63: NA | AE63: I followed the instructions and I have not yet listened to it! | AF63: Yes | AG63: 6 | AH63: Yes | AJ63: 43410.691 | AK63: SHJ
A64: =VLOOKUP(H64,Languages!$A$2:$B$430,2,FALSE) -> Afro-Asiatic | B64: Mourning | C64: Middle East | D64: Druze | E64: arab1395 | F64: arab1395 | G64: leva1239 | H64: =VLOOKUP(G64,'languoid 4.0'!$A$1:$I$24439,2,FALSE) -> afro1255 | I64: =VLOOKUP(G64,'languoid 4.0'!$A$1:$I$24439,6,FALSE) -> family | J64: yes | K64: yes | L64: yes | O64: Exact Match | P64: I'm sure | Q64: Nadb for a Deceased Girl | R64: https://folkways.si.edu/fawz-al-arfush/nadb-for-a-deceased-girl/islamica-world/music/track/smithsonian | S64: Disc 1, Track 3 | T64: Smithsonian Folkways | U64: No secondary function | V64: No | Z64: The song is identified as such in its title or label | AA64: Nadb for a Deceased Girl (Album: Laments of Lebanon - Funeral Laments) //SMITHSONIAN FOLKWAYS CATALOGUE NUMBER: FW04046_103// | AB64: NA | AC64: NA | AE64: I followed the instructions and I have not yet listened to it! | AF64: Yes | AG64: 6 | AH64: Yes | AJ64: 43410.693 | AK64: SHJ
A65: =VLOOKUP(H65,Languages!$A$2:$B$430,2,FALSE) -> Afro-Asiatic | B65: Mourning | C65: Middle East | D65: Druze | E65: arab1395 | F65: arab1395 | G65: leva1239 | H65: =VLOOKUP(G65,'languoid 4.0'!$A$1:$I$24439,2,FALSE) -> afro1255 | I65: =VLOOKUP(G65,'languoid 4.0'!$A$1:$I$24439,6,FALSE) -> family | J65: yes | K65: yes | L65: yes | O65: Exact Match | P65: I'm sure | Q65: Tahnin for a Deceased Girl | R65: https://folkways.si.edu/fawz-al-arfush/tahnin-for-a-deceased-girl/islamica-world/music/track/smithsonian | S65: Disc 1, Track 4 | T65: Smithsonian Folkways | U65: No secondary function | V65: No | Z65: The song is identified as such in its title or label | AA65: Tahnin for a Deceased Girl (Album: Laments of Lebanon - Funeral Laments) //SMITHSONIAN FOLKWAYS CATALOGUE NUMBER: FW04046_104// | AB65: NA | AC65: NA | AE65: I followed the instructions and I have not yet listened to it! | AF65: Yes | AG65: 6 | AH65: Yes | AJ65: 43410.694 | AK65: SHJ
A66: =VLOOKUP(H66,Languages!$A$2:$B$430,2,FALSE) -> Afro-Asiatic | B66: Mourning | C66: Middle East | D66: Druze | E66: arab1395 | F66: arab1395 | G66: leva1239 | H66: =VLOOKUP(G66,'languoid 4.0'!$A$1:$I$24439,2,FALSE) -> afro1255 | I66: =VLOOKUP(G66,'languoid 4.0'!$A$1:$I$24439,6,FALSE) -> family | J66: yes | K66: yes | L66: yes | O66: Exact Match | P66: I'm sure | Q66: Fraqiyyat for a Young Woman; the Last Verse for a Deceased Father | R66: https://folkways.si.edu/fawz-al-arfush/fraqiyyat-for-a-young-woman-the-last-verse-for-a-deceased-father/islamica-world/music/track/smithsonian | S66: Disc 1, Track 5 | T66: Smithsonian Folkways | U66: No secondary function | V66: No | Z66: The song is identified as such in its title or label | AA66: The Last Verse for a Deceased Far (Album: Laments of Lebanon - Funeral Laments) //SMITHSONIAN FOLKWAYS CATALOGUE NUMBER: FW04046_105// | AB66: NA | AC66: NA | AE66: I followed the instructions and I have not yet listened to it! | AF66: Yes | AG66: 6 | AH66: Yes | AJ66: 43410.695 | AK66: SHJ
A67: =VLOOKUP(H67,Languages!$A$2:$B$430,2,FALSE) -> Afro-Asiatic | B67: Mourning | C67: Middle East | D67: Druze | E67: arab1395 | F67: arab1395 | G67: leva1239 | H67: =VLOOKUP(G67,'languoid 4.0'!$A$1:$I$24439,2,FALSE) -> afro1255 | I67: =VLOOKUP(G67,'languoid 4.0'!$A$1:$I$24439,6,FALSE) -> family | J67: yes | K67: yes | L67: yes | O67: Exact Match | P67: I'm sure | Q67: Nadb Lamenting Ill-Fate, Possibly for a Deceased Parent | R67: https://folkways.si.edu/fawz-al-arfush/nadb-lamenting-ill-fate-possibly-for-a-deceased-parent/islamica-world/music/track/smithsonian | S67: Disc 1, Track 6 | T67: Smithsonian Folkways | U67: No secondary function | V67: No | Z67: The song is identified as such in its title or label | AA67: Nadb Lamenting Ill-Fate, Possibly for a Deceased Parent (Album: Laments of Lebanon - Funeral Laments) //SMITHSONIAN FOLKWAYS CATALOGUE NUMBER: FW04046_106// | AB67: NA | AC67: NA | AE67: I followed the instructions and I have not yet listened to it! | AF67: Yes | AG67: 6 | AH67: Yes | AJ67: 43410.697 | AK67: SHJ
A68: =VLOOKUP(H68,Languages!$A$2:$B$430,2,FALSE) -> Afro-Asiatic | B68: Mourning | C68: Middle East | D68: Druze | E68: arab1395 | F68: arab1395 | G68: leva1239 | H68: =VLOOKUP(G68,'languoid 4.0'!$A$1:$I$24439,2,FALSE) -> afro1255 | I68: =VLOOKUP(G68,'languoid 4.0'!$A$1:$I$24439,6,FALSE) -> family | J68: yes | K68: yes | L68: yes | O68: Exact Match | P68: I'm sure | Q68: Qasidah Sung for Nazirah Junbulat, a Deceased Woman of Distinguished Social and Political Stature | R68: https://folkways.si.edu/salman-al-arfush/qaidah-sung-for-nairah-junbula-a-deceased-woman-of-distinguished-social-and-political-stature/islamica-world/music/track/smithsonian | S68: Disc 1, Track 8 | T68: Smithsonian Folkways | U68: No secondary function | V68: No | Z68: The song is identified as such in its title or label | AA68: Qasidah Sung for Nazirah Junbulat, a Deceased Woman of Distinguished Social and Political Stature (Album: Laments of Lebanon - Funeral Laments) //SMITHSONIAN FOLKWAYS CATALOGUE NUMBER: FW04046_108// | AB68: NA | AC68: NA | AE68: I followed the instructions and I have not yet listened to it! | AF68: Yes | AG68: 6 | AH68: Yes | AJ68: 43410.699 | AK68: SHJ
A69: =VLOOKUP(H69,Languages!$A$2:$B$430,2,FALSE) -> Afro-Asiatic | B69: Mourning | C69: Middle East | D69: Druze | E69: arab1395 | F69: arab1395 | G69: leva1239 | H69: =VLOOKUP(G69,'languoid 4.0'!$A$1:$I$24439,2,FALSE) -> afro1255 | I69: =VLOOKUP(G69,'languoid 4.0'!$A$1:$I$24439,6,FALSE) -> family | J69: yes | K69: yes | L69: yes | O69: Exact Match | P69: I'm sure | Q69: Nadb for a Deceased Boy | R69: https://folkways.si.edu/salman-al-arfush/nadb-for-a-deceased-boy/islamica-world/music/track/smithsonian | S69: Disc 1, Track 9 | T69: Smithsonian Folkways | U69: No secondary function | V69: No | Z69: The song is identified as such in its title or label | AA69: Nadb for a Deceased Boy (Album: Laments of Lebanon - Funeral Laments) //SMITHSONIAN FOLKWAYS CATALOGUE NUMBER: FW04046_109// | AB69: NA | AC69: NA | AE69: I followed the instructions and I have not yet listened to it! | AF69: Yes | AG69: 6 | AH69: Yes | AJ69: 43410.7 | AK69: SHJ
A70: =VLOOKUP(H70,Languages!$A$2:$B$430,2,FALSE) -> Afro-Asiatic | B70: Mourning | C70: Northern Africa | D70: Tuareg | E70: tuar1240 | F70: tuar1240 | G70: tuar1240 | H70: =VLOOKUP(G70,'languoid 4.0'!$A$1:$I$24439,2,FALSE) -> afro1255 | I70: =VLOOKUP(G70,'languoid 4.0'!$A$1:$I$24439,6,FALSE) -> family | J70: yes | K70: yes | L70: yes | N70: tmh | O70: Most Common Subfamily | P70: I'm sure | Q70: Mourning for a Village Chief | R70: https://theglobaljukebox.org/?share=Tuareg-T5521R46 | S70: NA | T70: Global Jukebox | U70: No secondary function | V70: No | Z70: The song is identified as such in its title or label | AA70: Morning Song | AB70: he women sing while the men, riding camels, parade up and down. | AC70: NA | AE70: I followed the instructions and I have not yet listened to it! | AF70: Yes | AG70: 5 | AH70: Yes | AJ70: 43197.914 | AK70: RJW
A71: =VLOOKUP(H71,Languages!$A$2:$B$430,2,FALSE) -> Afro-Asiatic | B71: Praise | C71: Central Africa | D71: Arabs of Ouaddai | E71: chad1249 | F71: chad1249 | G71: chad1249 | H71: =VLOOKUP(G71,'languoid 4.0'!$A$1:$I$24439,2,FALSE) -> afro1255 | I71: =VLOOKUP(G71,'languoid 4.0'!$A$1:$I$24439,6,FALSE) -> language | J71: yes | K71: yes | L71: yes | N71: shu | O71: Exact Match | P71: I'm sure | Q71: Ouaddai: Praise to the Sultan's wife | R71: https://archives.crem-cnrs.fr/archives/items/CNRSMH_I_1994_002_001_01/ | S71: Disc 1, Track 1 | T71: CREM | U71: No secondary function | V71: No | Z71: The song is identified as such in its title or label, There is text in associated ethnography that states what type of song this is (this could be in liner notes, it could be in an email from an anthropologist, etc) | AA71: Ouaddai: Praise to the Sultan's wife//CODING ID CNRSMH_I_1994_002_001_01 IN CREM, RELEVANT TEXT IS IN THE TITLE FIELD// | AB71: Recording done at the request of the singer, aged 80 years. Praise for the Sultan's wife//CODING ID CNRSMH_I_1994_002_001_01 IN CREM, RELEVANT TEXT IS IN THE ETHNOGRAPHIC CONTEXT FIELD// | AC71: NA | AE71: I followed the instructions and I have not yet listened to it! | AF71: Yes | AG71: 6 | AH71: Yes | AJ71: 7/14/2018 11:03:06 | AK71: NCM
A72: =VLOOKUP(H72,Languages!$A$2:$B$430,2,FALSE) -> Afro-Asiatic | B72: Praise | C72: Eastern Africa | D72: Ajuran | E72: nort3051 | F72: soma1255 | G72: nort3051 | H72: =VLOOKUP(G72,'languoid 4.0'!$A$1:$I$24439,2,FALSE) -> afro1255 | I72: =VLOOKUP(G72,'languoid 4.0'!$A$1:$I$24439,6,FALSE) -> dialect | J72: no | K72: yes | L72: yes | O72: Exact Match | P72: I'm not sure | Q72: Praise of King | R72: http://media.theglobaljukebox.org/audio/T5561R04.mp3 | S72: N/A | T72: Global Jukebox | U72: Responsorial song; song about leadership; song for royalty | V72: No | Z72: The song is identified as such in its title or label | AA72: Praise song //GLOBAL JUKEBOX, CODING ID 9976, AUDIO FILE ID T5561R04// | AB72: N/A | AC72: N/A | AD72: Global Jukebox-->Ajuran-->Praise of King | AE72: I followed the instructions and I have not yet listened to it! | AF72: Yes | AG72: 6 | AH72: Yes | AJ72: 43437.491 | AK72: ERA
A73: =VLOOKUP(H73,Languages!$A$2:$B$430,2,FALSE) -> Afro-Asiatic | B73: Praise | C73: Eastern Africa | D73: Amhara | E73: amha1245 | F73: amha1245 | G73: amha1245 | H73: =VLOOKUP(G73,'languoid 4.0'!$A$1:$I$24439,2,FALSE) -> afro1255 | I73: =VLOOKUP(G73,'languoid 4.0'!$A$1:$I$24439,6,FALSE) -> language | J73: yes | K73: yes | L73: yes | N73: amh | O73: Exact Match | P73: I'm sure | Q73: Song of Praise 'Eritrea' | R73: http://media.theglobaljukebox.org/audio/T45020.mp3 | S73: N/A | T73: Global Jukebox, Smithsonian Folkways | U73: song about leadership; song for royalty | V73: No | Z73: The song is identified as such in its title or label, The lyrics made it clear to me what type of song this is | AA73: Praise song //GLOBAL JUKEBOX, CODING ID 708, AUDIO FILE ID T45020// | AB73: N/A | AC73: "The Son of Ras Makonnen will feed us/ His justice is like that of an angel/ May God give long life to Haile Selassie/ the child of our country" //GLOBAL JUKEBOX, CODING ID 708, AUDIO FILE ID T45020// | AD73: Global Jukebox-->Amhara-->Song of Praise 'Eritrea' | AE73: I followed the instructions and I have not yet listened to it! | AF73: Yes | AG73: 4 | AH73: Yes | AJ73: 43437.495 | AK73: ERA
A74: =VLOOKUP(H74,Languages!$A$2:$B$430,2,FALSE) -> Afro-Asiatic | B74: Praise | C74: Eastern Africa | D74: Amhara | E74: amha1245 | F74: amha1245 | G74: amha1245 | H74: =VLOOKUP(G74,'languoid 4.0'!$A$1:$I$24439,2,FALSE) -> afro1255 | I74: =VLOOKUP(G74,'languoid 4.0'!$A$1:$I$24439,6,FALSE) -> language | J74: yes | K74: yes | L74: yes | N74: amh | O74: Exact Match | P74: I'm sure | Q74: Song for the Emperor | R74: http://media.theglobaljukebox.org/audio/T5523R23.mp3 | S74: N/A | T74: Global Jukebox, Smithsonian Folkways | U74: song about leadership; song for royalty | V74: No | Z74: The song is identified as such in its title or label, There is text in associated ethnography that states what type of song this is (this could be in liner notes, it could be in an email from an anthropologist, etc) | AA74: Praise Song //GLOBAL JUKEBOX, CODING ID 9208, AUDIO FILE ID T5523R23// | AB74: Song praising the Emperor Haile Selassie //GLOBAL JUKEBOX, CODING ID 9208, AUDIO FILE ID T5523R23// | AC74: N/A | AD74: Global Jukebox-->Amhara-->Song for the Emperor | AE74: I followed the instructions and I have not yet listened to it! | AF74: Yes | AG74: 4 | AH74: Yes | AJ74: 43437.497 | AK74: ERA
A75: =VLOOKUP(H75,Languages!$A$2:$B$430,2,FALSE) -> Afro-Asiatic | B75: Praise | C75: Eastern Africa | D75: Listed as Hawazma. Tribe of Maggara / Hemat. | E75: bath1248 | F75: arab1395 | G75: suda1236 | H75: =VLOOKUP(G75,'languoid 4.0'!$A$1:$I$24439,2,FALSE) -> afro1255 | I75: =VLOOKUP(G75,'languoid 4.0'!$A$1:$I$24439,6,FALSE) -> language | J75: no | K75: yes | L75: yes | O75: Exact Match | P75: I'm sure | Q75: Hajjin Praise Song | R75: https://theglobaljukebox.org/?share=Hawazma-T5625R20m | S75: NA | T75: Global Jukebox | U75: No secondary function | V75: No | Z75: The song is identified as such in its title or label | AA75: Hajjin Praise Song //GLOBAL JUKEBOX CODING ID 4213: SONG, GENRE, DESCRIPTION// | AB75: NA | AC75: NA | AE75: I followed the instructions and I have not yet listened to it! | AF75: Yes | AG75: 6 | AH75: Yes | AJ75: 4/16/2018 11:54:49 | AK75: MJW
A76: =VLOOKUP(H76,Languages!$A$2:$B$430,2,FALSE) -> Afro-Asiatic | B76: Praise | C76: Eastern Africa | D76: Baggara / Hemat | E76: bath1248 | F76: arab1395 | G76: bath1248 | H76: =VLOOKUP(G76,'languoid 4.0'!$A$1:$I$24439,2,FALSE) -> afro1255 | I76: =VLOOKUP(G76,'languoid 4.0'!$A$1:$I$24439,6,FALSE) -> dialect | J76: no | K76: yes | L76: yes | O76: Exact Match | P76: I'm sure | Q76: Praise to Tribal Horses and Horsemen of the Beni Halba | R76: https://theglobaljukebox.org/?share=Baggara-T5626R22m | S76: NA | T76: Global Jukebox | U76: No secondary function | V76: No | Z76: There is text in associated ethnography that states what type of song this is (this could be in liner notes, it could be in an email from an anthropologist, etc) | AA76: NA | AB76: Praise to Tribal Horses and Horsemen of the Beni Halba //GLOBAL JUKEBOX: CODING ID 4199, DESCRIPTION// | AC76: NA | AD76: click on green checklist icon or track title in lower right | AE76: I followed the instructions and I have not yet listened to it! | AF76: Yes | AG76: 6 | AH76: Yes | AJ76: 4/18/2018 11:59:37 | AK76: MJW
A77: =VLOOKUP(H77,Languages!$A$2:$B$430,2,FALSE) -> Afro-Asiatic | B77: Praise | C77: Northern Africa | D77: Sahrawi: Hassaniya | E77: hass1238 | F77: arab1395 | G77: hass1238 | H77: =VLOOKUP(G77,'languoid 4.0'!$A$1:$I$24439,2,FALSE) -> afro1255 | I77: =VLOOKUP(G77,'languoid 4.0'!$A$1:$I$24439,6,FALSE) -> language | J77: no | K77: yes | L77: yes | N77: mey | O77: Exact Match | P77: I'm sure | Q77: Gajmi Fulana | R77: https://sounds.bl.uk/World-and-traditional-music/Violeta-Ruano-portraits-of-Saharawi-Music/025M-C1640X0132XX-0001V0 | S77: NA | T77: British Library | U77: No secondary function | V77: No | Z77: The song is identified as such in its title or label, There is text in associated ethnography that states what type of song this is (this could be in liner notes, it could be in an email from an anthropologist, etc) | AA77: Praise songs //BRITISH LIBRARY, VIOLETA RUANO PORTRAITS OF SAHARAWI MUSIC, GENRE// | AB77: This is a traditional verse that praises a tribe from the south of Mauritania. It is performed in the mode lebteit. //BRITISH LIBRARY, SHELF MARK C1640/132, VIOLETA RUANO PORTRAITS OF SAHARAWI MUSIC, ABSTRACT// | AC77: NA | AE77: I followed the instructions and I have not yet listened to it! | AF77: Yes | AG77: 5 | AH77: Yes | AJ77: 43348.634 | AK77: MJW
A78: =VLOOKUP(H78,Languages!$A$2:$B$430,2,FALSE) -> Afro-Asiatic | B78: Praise | C78: Northern Africa | D78: Sahrawi: Hassaniya | E78: hass1238 | F78: arab1395 | G78: hass1238 | H78: =VLOOKUP(G78,'languoid 4.0'!$A$1:$I$24439,2,FALSE) -> afro1255 | I78: =VLOOKUP(G78,'languoid 4.0'!$A$1:$I$24439,6,FALSE) -> language | J78: no | K78: yes | L78: yes | N78: mey | O78: Exact Match | P78: I'm sure | Q78: Banda hamai | R78: https://sounds.bl.uk/World-and-traditional-music/Violeta-Ruano-portraits-of-Saharawi-Music/025M-C1640X0031XX-0001V0 | S78: NA | T78: British Library | U78: Dance | V78: No | Z78: There is text in associated ethnography that states what type of song this is (this could be in liner notes, it could be in an email from an anthropologist, etc) | AA78: NA | AB78: Traditional music for dancing, especially in Mauritania, but also within Saharawi society.The performance occasion was a private session in the house of the musician. Luali Said is an extremely talented guitarist that performs regularly in national events and weddings in the camps. He has his own, very rich guitar playing style, especially when improvising. //BRITISH LIBRARY, SHELF MARK C1640/31, VIOLETA RUANO PORTRAITS OF SAHARAWI MUSIC, ABSTRACT// | AC78: NA | AE78: I followed the instructions and I have not yet listened to it! | AF78: No | AG78: 1 | AH78: Yes | AJ78: 43348.637 | AK78: MJW
A79: =VLOOKUP(H79,Languages!$A$2:$B$430,2,FALSE) -> Afro-Asiatic | B79: Praise | C79: Northern Africa | D79: Baggara | E79: bath1248 | F79: arab1395 | G79: bath1248 | H79: =VLOOKUP(G79,'languoid 4.0'!$A$1:$I$24439,2,FALSE) -> afro1255 | I79: =VLOOKUP(G79,'languoid 4.0'!$A$1:$I$24439,6,FALSE) -> dialect | J79: no | K79: yes | L79: yes | O79: Exact Match | P79: I'm sure | Q79: Praise to Nazir and to Beni Halba Tribe | R79: https://theglobaljukebox.org/?share=Baggara-T5626R20m | S79: NA | T79: Global Jukebox | U79: No secondary function | V79: No | Z79: The song is identified as such in its title or label | AA79: Praise to Nazir and to Beni Halba Tribe | AB79: Praise to Nazir | AC79: NA | AE79: I followed the instructions and I have not yet listened to it! | AF79: Yes | AG79: 6 | AH79: Yes | AJ79: 6/24/2018 15:59:37 | AK79: RJW
A80: =VLOOKUP(H80,Languages!$A$2:$B$430,2,FALSE) -> Afro-Asiatic | B80: Praise | C80: Northern Africa | D80: Baggara | E80: bath1248 | F80: arab1395 | G80: bath1248 | H80: =VLOOKUP(G80,'languoid 4.0'!$A$1:$I$24439,2,FALSE) -> afro1255 | I80: =VLOOKUP(G80,'languoid 4.0'!$A$1:$I$24439,6,FALSE) -> dialect | J80: no | K80: yes | L80: yes | O80: Exact Match | P80: I'm sure | Q80: El Katim | R80: https://theglobaljukebox.org/?share=Baggara-T5626R19m | S80: NA | T80: Global Jukebox | U80: No secondary function | V80: No | Z80: The song is identified as such in its title or label | AA80: Praise to Nazir | AB80: Praise to Nazir | AC80: NA | AE80: I followed the instructions and I have not yet listened to it! | AF80: Yes | AG80: 6 | AH80: Yes | AJ80: 6/24/2018 16:08:20 | AK80: RJW
A81: =VLOOKUP(H81,Languages!$A$2:$B$430,2,FALSE) -> Afro-Asiatic | B81: Praise | C81: Northern Africa | D81: Baggara | E81: bath1248 | F81: arab1395 | G81: bath1248 | H81: =VLOOKUP(G81,'languoid 4.0'!$A$1:$I$24439,2,FALSE) -> afro1255 | I81: =VLOOKUP(G81,'languoid 4.0'!$A$1:$I$24439,6,FALSE) -> dialect | J81: no | K81: yes | L81: yes | O81: Exact Match | P81: I'm sure | Q81: Ka'atim Praises Ta'aisha Youths | R81: https://theglobaljukebox.org/?share=Baggara-T5626R17m# | S81: NA | T81: Global Jukebox | U81: No secondary function | V81: No | Z81: The song is identified as such in its title or label | AA81: Ka'atim Praises Ta'aisha Youths | AB81: Praise song | AC81: NA | AE81: I followed the instructions and I have not yet listened to it! | AF81: Yes | AG81: 6 | AH81: Yes | AJ81: 6/24/2018 16:16:25 | AK81: RJW
A82: =VLOOKUP(H82,Languages!$A$2:$B$430,2,FALSE) -> Afro-Asiatic | B82: Praise | C82: Northern Africa | D82: Baggara | E82: bath1248 | F82: arab1395 | G82: bath1248 | H82: =VLOOKUP(G82,'languoid 4.0'!$A$1:$I$24439,2,FALSE) -> afro1255 | I82: =VLOOKUP(G82,'languoid 4.0'!$A$1:$I$24439,6,FALSE) -> dialect | J82: no | K82: yes | L82: yes | O82: Exact Match | P82: I'm sure | Q82: Praise to Boys' Character | R82: https://theglobaljukebox.org/?share=Baggara-T5626R16m# | S82: NA | T82: Global Jukebox | U82: No secondary function | V82: No | Z82: The song is identified as such in its title or label | AA82: Praise to Boys' Character | AB82: NA | AC82: NA | AE82: I followed the instructions and I have not yet listened to it! | AF82: Yes | AG82: 6 | AH82: Yes | AJ82: 6/24/2018 16:31:49 | AK82: RJW
A83: =VLOOKUP(H83,Languages!$A$2:$B$430,2,FALSE) -> Afro-Asiatic | B83: Praise | C83: Northern Africa | D83: Baggara | E83: bath1248 | F83: arab1395 | G83: bath1248 | H83: =VLOOKUP(G83,'languoid 4.0'!$A$1:$I$24439,2,FALSE) -> afro1255 | I83: =VLOOKUP(G83,'languoid 4.0'!$A$1:$I$24439,6,FALSE) -> dialect | J83: no | K83: yes | L83: yes | O83: Exact Match | P83: I'm sure | Q83: Ka'atim Praises Ta'aisha Youths | R83: https://theglobaljukebox.org/?share=Baggara-T5626R17m | S83: NA | T83: Global Jukebox | U83: No secondary function | V83: No | Z83: The song is identified as such in its title or label | AA83: Ka'atim Praises Ta'aisha Youths | AB83: Praise song | AC83: NA | AE83: I followed the instructions and I have not yet listened to it! | AF83: Yes | AG83: 6 | AH83: Yes | AJ83: 6/24/2018 16:35:54 | AK83: RJW
A84: =VLOOKUP(H84,Languages!$A$2:$B$430,2,FALSE) -> Afro-Asiatic | B84: Praise | C84: Northern Africa | D84: Baggara | E84: bath1248 | F84: arab1395 | G84: bath1248 | H84: =VLOOKUP(G84,'languoid 4.0'!$A$1:$I$24439,2,FALSE) -> afro1255 | I84: =VLOOKUP(G84,'languoid 4.0'!$A$1:$I$24439,6,FALSE) -> dialect | J84: no | K84: yes | L84: yes | O84: Exact Match | P84: I'm sure | Q84: Praise Song for Sanussi | R84: https://theglobaljukebox.org/?share=Baggara-T5626R14m | S84: NA | T84: Global Jukebox | U84: No secondary function | V84: No | Z84: The song is identified as such in its title or label | AA84: Praise Song for Sanussi | AB84: Praise song | AC84: NA | AE84: I followed the instructions and I have not yet listened to it! | AF84: Yes | AG84: 6 | AH84: Yes | AJ84: 6/24/2018 16:49:08 | AK84: RJW
A85: =VLOOKUP(H85,Languages!$A$2:$B$430,2,FALSE) -> Afro-Asiatic | B85: Praise | C85: Northern Africa | D85: Baggara | E85: bath1248 | F85: arab1395 | G85: bath1248 | H85: =VLOOKUP(G85,'languoid 4.0'!$A$1:$I$24439,2,FALSE) -> afro1255 | I85: =VLOOKUP(G85,'languoid 4.0'!$A$1:$I$24439,6,FALSE) -> dialect | J85: no | K85: yes | L85: yes | O85: Exact Match | P85: I'm sure | Q85: Praise to Tribal Horses and Horsemen of the Beni Halba | R85: https://theglobaljukebox.org/?share=Baggara-T5626R22m | S85: NA | T85: Global Jukebox | U85: No secondary function | V85: No | Z85: The song is identified as such in its title or label | AA85: Praise to Tribal Horses and Horsemen of the Beni Halba | AB85: Praise to Tribal Horses and Horsemen of the Beni Halba | AC85: NA | AE85: I followed the instructions and I have not yet listened to it! | AF85: Yes | AG85: 5 | AH85: Yes | AJ85: 6/24/2018 16:54:11 | AK85: RJW
A86: =VLOOKUP(H86,Languages!$A$2:$B$430,2,FALSE) -> Afro-Asiatic | B86: Praise | C86: Northern Africa | D86: Hawazma | E86: bath1248 | F86: arab1395 | G86: suda1236 | H86: =VLOOKUP(G86,'languoid 4.0'!$A$1:$I$24439,2,FALSE) -> afro1255 | I86: =VLOOKUP(G86,'languoid 4.0'!$A$1:$I$24439,6,FALSE) -> language | J86: no | K86: yes | L86: yes | O86: Exact Match | P86: I'm sure | Q86: Hajjin Praise Song | R86: https://theglobaljukebox.org/?share=Hawazma-T5625R20m | S86: NA | T86: Global Jukebox | U86: No secondary function | V86: No | Z86: The song is identified as such in its title or label | AA86: Hajjin Praise Song | AB86: Praise song | AC86: NA | AE86: I followed the instructions and I have not yet listened to it! | AF86: Yes | AG86: 6 | AH86: Yes | AJ86: 6/24/2018 17:03:09 | AK86: RJW
A87: =VLOOKUP(H87,Languages!$A$2:$B$430,2,FALSE) -> Afro-Asiatic | B87: Praise | C87: Northern Africa | D87: Hawazma | E87: bath1248 | F87: arab1395 | G87: suda1236 | H87: =VLOOKUP(G87,'languoid 4.0'!$A$1:$I$24439,2,FALSE) -> afro1255 | I87: =VLOOKUP(G87,'languoid 4.0'!$A$1:$I$24439,6,FALSE) -> language | J87: no | K87: yes | L87: yes | O87: Exact Match | P87: I'm sure | Q87: Praise Song to Soldiers | R87: https://theglobaljukebox.org/?share=Hawazma-T5625R21m | S87: NA | T87: Global Jukebox | U87: No secondary function | V87: No | Z87: The song is identified as such in its title or label | AA87: Praise Song to Soldiers | AB87: Praise song to soldiers fighting in South Sudan | AC87: NA | AE87: I followed the instructions and I have not yet listened to it! | AF87: Yes | AG87: 6 | AH87: Yes | AJ87: 6/24/2018 17:13:20 | AK87: RJW
A88: =VLOOKUP(H88,Languages!$A$2:$B$430,2,FALSE) -> Afro-Asiatic | B88: Praise | C88: Northern Africa | D88: Hawazma | E88: bath1248 | F88: arab1395 | G88: suda1236 | H88: =VLOOKUP(G88,'languoid 4.0'!$A$1:$I$24439,2,FALSE) -> afro1255 | I88: =VLOOKUP(G88,'languoid 4.0'!$A$1:$I$24439,6,FALSE) -> language | J88: no | K88: yes | L88: yes | O88: Exact Match | P88: I'm sure | Q88: Praise Song for Hassin & Marobrub | R88: https://theglobaljukebox.org/?share=Hawazma-T5625R23m | S88: NA | T88: Global Jukebox | U88: No secondary function | V88: No | Z88: The song is identified as such in its title or label | AA88: Praise Song for Hassin & Marobrub | AB88: Praise song | AC88: NA | AE88: I followed the instructions and I have not yet listened to it! | AF88: Yes | AG88: 6 | AH88: Yes | AJ88: 6/24/2018 17:16:14 | AK88: RJW
A89: =VLOOKUP(H89,Languages!$A$2:$B$430,2,FALSE) -> Afro-Asiatic | B89: Praise | C89: Western Africa | D89: Hausa | E89: haus1257 | F89: haus1257 | G89: haus1257 | H89: =VLOOKUP(G89,'languoid 4.0'!$A$1:$I$24439,2,FALSE) -> afro1255 | I89: =VLOOKUP(G89,'languoid 4.0'!$A$1:$I$24439,6,FALSE) -> language | J89: yes | K89: yes | L89: yes | N89: hau | O89: Exact Match | P89: I'm sure | Q89: Jauje Praise Music | R89: https://theglobaljukebox.org/?share=Hausa-T5621R08m | S89: NA | T89: Global Jukebox | U89: No secondary function | V89: No | Z89: The song is identified as such in its title or label | AA89: Praise Song//GLOBAL JUKEBOX CODING ID 1939/AUDIO FILE ID T5621R08m, RELEVANT TEXT IS IN THE GENRE FIELD// | AB89: Praise music at the waza//GLOBAL JUKEBOX CODING ID 1939/AUDIO FILE ID T5621R08m, RELEVANT TEXT IS IN THE DESCRIPTION FIELD// | AC89: NA | AE89: I followed the instructions and I have not yet listened to it! | AF89: Yes | AG89: 6 | AH89: Yes | AJ89: 43441.568 | AK89: JMI
A90: =VLOOKUP(H90,Languages!$A$2:$B$430,2,FALSE) -> Afro-Asiatic | B90: Praise | C90: Western Africa | D90: Hausa | E90: haus1257 | F90: haus1257 | G90: haus1257 | H90: =VLOOKUP(G90,'languoid 4.0'!$A$1:$I$24439,2,FALSE) -> afro1255 | I90: =VLOOKUP(G90,'languoid 4.0'!$A$1:$I$24439,6,FALSE) -> language | J90: yes | K90: yes | L90: yes | N90: hau | O90: Exact Match | P90: I'm sure | Q90: Praise Song for the Galadima of Zaria | R90: https://theglobaljukebox.org/?share=Hausa-T5621R10m | S90: NA | T90: Global Jukebox | U90: No secondary function | V90: No | Z90: The song is identified as such in its title or label | AA90: Praise song; song about leadership//GLOBAL JUKEBOX CODING ID 1938/AUDIO FILE ID T5621R10m, RELEVANT TEXT IS IN THE GENRE FIELD// | AB90: The Galadima was a noble and top offcial under the Emir in the pyramidal political structure of Hausa society//GLOBAL JUKEBOX CODING ID 1938/AUDIO FILE ID T5621R10m, RELEVANT TEXT IS IN THE DESCRIPTION FIELD// | AC90: NA | AE90: I followed the instructions and I have not yet listened to it! | AF90: Yes | AG90: 6 | AH90: Yes | AJ90: 43441.571 | AK90: JMI
A91: =VLOOKUP(H91,Languages!$A$2:$B$430,2,FALSE) -> Afro-Asiatic | B91: Praise | C91: Western Africa | D91: Hausa | E91: haus1257 | F91: haus1257 | G91: haus1257 | H91: =VLOOKUP(G91,'languoid 4.0'!$A$1:$I$24439,2,FALSE) -> afro1255 | I91: =VLOOKUP(G91,'languoid 4.0'!$A$1:$I$24439,6,FALSE) -> language | J91: yes | K91: yes | L91: yes | N91: hau | O91: Exact Match | P91: I'm sure | Q91: Praise Song for the Galadima of Zaria | R91: https://theglobaljukebox.org/?share=Hausa-T5621R09m | S91: NA | T91: Global Jukebox | U91: No secondary function | V91: No | Z91: The song is identified as such in its title or label | AA91: Praise song; song about leadership//GLOBAL JUKEBOX CODING ID 1940/AUDIO FILE ID T5621R09m, RELEVANT TEXT IS IN THE GENRE FIELD// | AB91: The Galadima was a noble and top offcial under the Emir in the pyramidal political structure of Hausa society//GLOBAL JUKEBOX CODING ID 1940/AUDIO FILE ID T5621R09m, RELEVANT TEXT IS IN THE DESCRIPTION FIELD// | AC91: NA | AE91: I followed the instructions and I have not yet listened to it! | AF91: Yes | AG91: 6 | AH91: Yes | AJ91: 43441.576 | AK91: JMI
A92: =VLOOKUP(H92,Languages!$A$2:$B$430,2,FALSE) -> Afro-Asiatic | B92: Praise | C92: Western Africa | D92: Hausa | E92: haus1257 | F92: haus1257 | G92: haus1257 | H92: =VLOOKUP(G92,'languoid 4.0'!$A$1:$I$24439,2,FALSE) -> afro1255 | I92: =VLOOKUP(G92,'languoid 4.0'!$A$1:$I$24439,6,FALSE) -> language | J92: yes | K92: yes | L92: yes | N92: hau | O92: Exact Match | P92: I'm sure | Q92: Banga Praise Music for the Vassal Chief of Kauru | R92: https://theglobaljukebox.org/?share=Hausa-T5621R07m | S92: NA | T92: Global Jukebox | U92: No secondary function | V92: No | Z92: The song is identified as such in its title or label | AA92: Praise song; song about leadership; chief's song//GLOBAL JUKEBOX CODING ID 1941/AUDIO FILE ID T5621R07m, RELEVANT TEXT IS IN THE GENRE FIELD// | AB92: Praise Music for Vassal Chief of Kauru; for the weekly congregation of musicians of the chief in front of his palace, waza//GLOBAL JUKEBOX CODING ID 1941/AUDIO FILE ID T5621R07m, RELEVANT TEXT IS IN THE DESCRIPTION FIELD// | AC92: NA | AE92: I followed the instructions and I have not yet listened to it! | AF92: Yes | AG92: 6 | AH92: Yes | AJ92: 43441.579 | AK92: JMI
A93: =VLOOKUP(H93,Languages!$A$2:$B$430,2,FALSE) -> Afro-Asiatic | B93: Praise | C93: Western Africa | D93: Hausa | E93: haus1257 | F93: haus1257 | G93: haus1257 | H93: =VLOOKUP(G93,'languoid 4.0'!$A$1:$I$24439,2,FALSE) -> afro1255 | I93: =VLOOKUP(G93,'languoid 4.0'!$A$1:$I$24439,6,FALSE) -> language | J93: yes | K93: yes | L93: yes | N93: hau | O93: Exact Match | P93: I'm sure | Q93: Goge Praise Song for NPC Political Party | R93: https://theglobaljukebox.org/?share=Hausa-T5621R04m | S93: NA | T93: Global Jukebox | U93: Political | V93: No | Z93: The song is identified as such in its title or label | AA93: Praise song; song about leadership; political song//GLOBAL JUKEBOX CODING ID 1944/AUDIO FILE ID T5621R04m, RELEVANT TEXT IS IN THE GENRE FIELD// | AB93: Praise of the NPC Party and its leader, the Sarduana//GLOBAL JUKEBOX CODING ID 1944/AUDIO FILE ID T5621R04m, RELEVANT TEXT IS IN THE DESCRIPTION FIELD// | AC93: NA | AE93: I followed the instructions and I have not yet listened to it! | AF93: Yes | AG93: 6 | AH93: Yes | AJ93: 43441.583 | AK93: JMI
A94: =VLOOKUP(H94,Languages!$A$2:$B$430,2,FALSE) -> Afro-Asiatic | B94: Praise | C94: Western Africa | D94: Hausa | E94: haus1257 | F94: haus1257 | G94: haus1257 | H94: =VLOOKUP(G94,'languoid 4.0'!$A$1:$I$24439,2,FALSE) -> afro1255 | I94: =VLOOKUP(G94,'languoid 4.0'!$A$1:$I$24439,6,FALSE) -> language | J94: yes | K94: yes | L94: yes | N94: hau | O94: Exact Match | P94: I'm sure | Q94: Praise Songs for Farming Bees | R94: https://theglobaljukebox.org/?share=Hausa-T5621R02m | S94: NA | T94: Global Jukebox | U94: No secondary function | V94: No | Z94: The song is identified as such in its title or label | AA94: Praise song; bee song//GLOBAL JUKEBOX CODING ID 1946/AUDIO FILE ID T5621R02m, RELEVANT TEXT IS IN THE GENRE FIELD// | AB94: Praise words are beaten and sung for each young man in the village, first stated on the big drum, then sung by the chorus as big drum continues to repeat it throughout//GLOBAL JUKEBOX CODING ID 1946/AUDIO FILE ID T5621R02m, RELEVANT TEXT IS IN THE DESCRIPTION FIELD// | AC94: NA | AE94: I followed the instructions and I have not yet listened to it! | AF94: Yes | AG94: 6 | AH94: Yes | AJ94: 43441.588 | AK94: JMI
A95: =VLOOKUP(H95,Languages!$A$2:$B$430,2,FALSE) -> Afro-Asiatic | B95: Procession | C95: Middle East | D95: Kathiri Bedouin, Awlaqi | E95: arab1395 | F95: arab1395 | G95: arab1393 | H95: =VLOOKUP(G95,'languoid 4.0'!$A$1:$I$24439,2,FALSE) -> afro1255 | I95: =VLOOKUP(G95,'languoid 4.0'!$A$1:$I$24439,6,FALSE) -> family | J95: yes | K95: yes | L95: yes | O95: Exact Match | P95: I'm sure | Q95: Gathering Song of the Tribe of Awlaqi | R95: http://media.theglobaljukebox.org/audio/T5482R01.mp3 | S95: NA | T95: Global Jukebox, Smithsonian Folkways | U95: No secondary function | V95: No | Z95: There is text in associated ethnography that states what type of song this is (this could be in liner notes, it could be in an email from an anthropologist, etc) | AA95: NA | AB95: Genre: Song for community gathering...Description:...the men start singing before they appear at the gathering place and continue with the song when they have arrived at the Tribal Convocation // CODING ID 712 IN GLOBAL JUKEBOX, RELEVANT TEXT IS IN THE DESCRIPTION FIELD// | AC95: NA | AE95: I followed the instructions and I have not yet listened to it! | AF95: Yes | AG95: 6 | AH95: Yes | AJ95: 43318.678 | AK95: SHJ
A96: =VLOOKUP(H96,Languages!$A$2:$B$430,2,FALSE) -> Afro-Asiatic | B96: Procession | C96: Northern Africa | D96: Atlas Berbers: Ait Bougmez | E96: atla1275 | F96: . | G96: atla1275 | H96: =VLOOKUP(G96,'languoid 4.0'!$A$1:$I$24439,2,FALSE) -> afro1255 | I96: =VLOOKUP(G96,'languoid 4.0'!$A$1:$I$24439,6,FALSE) -> family | J96: no | K96: . | L96: . | O96: Most Common Subfamily | P96: I'm sure | Q96: Chant de mariage des Ayt Bougmez | R96: http://archives.crem-cnrs.fr/archives/items/CNRSMH_E_1997_006_001_06/ | S96: NA | T96: CREM | U96: Wedding | V96: No | Z96: The song is identified as such in its title or label, There is text in associated ethnography that states what type of song this is (this could be in liner notes, it could be in an email from an anthropologist, etc) | AA96: Chant de mariage des Ayt Bougmez [= Wedding song from the Ait Bougmez] //CREM CNRSMH_E_1997_006_001_06 TITLE// | AB96: Ce chant est chanté en antiphonie par les femmes pour amener la mariée dans la maison du marié. [= This song is sung antiphonally by women to bring the bride to the groom's house.] //CREM CNRSMH_E_1997_006_001_06 ETHNOGRAPHIC CONTEXT// | AC96: NA | AE96: I followed the instructions and I have not yet listened to it! | AF96: Yes | AG96: 6 | AH96: Yes | AJ96: 43348.713 | AK96: MJW
A97: =VLOOKUP(H97,Languages!$A$2:$B$430,2,FALSE) -> Afro-Asiatic | B97: Procession | C97: Northern Africa | D97: Moroccan Berbers | E97: hogg1238 | F97: berb1260 | G97: berb1260 | H97: =VLOOKUP(G97,'languoid 4.0'!$A$1:$I$24439,2,FALSE) -> afro1255 | I97: =VLOOKUP(G97,'languoid 4.0'!$A$1:$I$24439,6,FALSE) -> family | J97: no | K97: yes | L97: yes | O97: Exact Match | P97: I'm sure | Q97: Aili ya Mali | R97: https://theglobaljukebox.org/?share=Moroccan%20Berbers-T5436R09m | S97: NS | T97: Global Jukebox | U97: No secondary function | V97: No | Z97: The song is identified as such in its title or label | AA97: Processional music | AB97: Processional music | AC97: NA | AH97: No | AJ97: 43197.911 | AK97: RJW
A98: =VLOOKUP(H98,Languages!$A$2:$B$430,2,FALSE) -> Afro-Asiatic | B98: Story | C98: Middle East | D98: Iraq | E98: arab1395 | F98: arab1395 | G98: arab1395 | H98: =VLOOKUP(G98,'languoid 4.0'!$A$1:$I$24439,2,FALSE) -> afro1255 | I98: =VLOOKUP(G98,'languoid 4.0'!$A$1:$I$24439,6,FALSE) -> family | J98: yes | K98: yes | L98: yes | O98: Exact Match | P98: I'm not sure | Q98: Ya Naees El-Tarfe | R98: http://media.theglobaljukebox.org/audio/T5554R11.mp3 | S98: NA | T98: Global Jukebox | U98: Praise | V98: No | Z98: There is text in associated ethnography that states what type of song this is (this could be in liner notes, it could be in an email from an anthropologist, etc) | AA98: Nostalgic song // CODING ID 9295 IN GLOBAL JUKEBOX, RELEVANT TEXT IS IN THE DESCRIPTION FIELD// | AB98: Genre: Nostalgic song, Description: Oh You with the Dreaming Eyes; nostalgic song recalling the days of chivalrous horsemen and brave warriors // CODING ID 9295 IN GLOBAL JUKEBOX // | AC98: NA | AE98: I followed the instructions and I have not yet listened to it! | AF98: Yes | AG98: 6 | AH98: Yes | AJ98: 43318.631 | AK98: SHJ
A99: =VLOOKUP(H99,Languages!$A$2:$B$430,2,FALSE) -> Afro-Asiatic | B99: Story | C99: Northern Africa | D99: Atlas Berbers | E99: cent2194 | F99: . | G99: cent2194 | H99: =VLOOKUP(G99,'languoid 4.0'!$A$1:$I$24439,2,FALSE) -> afro1255 | I99: =VLOOKUP(G99,'languoid 4.0'!$A$1:$I$24439,6,FALSE) -> language | J99: no | K99: . | L99: . | N99: tzm | O99: Exact Match | P99: I'm sure | Q99: Qsida Midh | R99: https://www.youtube.com/watch?v=5UK0aljqO2c | S99: Disc 4, Track 3 | T99: Global Jukebox, Smithsonian Folkways | U99: Praise | V99: No | Z99: The song is identified as such in its title or label, There is text in associated ethnography that states what type of song this is (this could be in liner notes, it could be in an email from an anthropologist, etc) | AA99: Ballad; praise song //GLOBAL JUKEBOX CODING ID 1586 GENRE// | AB99: Ballad in honor of the Prophet Mohammed; lyrics by Sidi ben Ali; sung in ancient Moghrebi //GLOBAL JUKEBOX CODING ID 1586 DESCRIPTION// | AC99: NA | AD99: Found in the CD "Music of Morocco: from the Library of Congress" (recorded by Paul Bowles, 1959) | AE99: I followed the instructions and I have not yet listened to it! | AF99: Yes | AG99: 6 | AH99: Yes | AI99: Doesn't appear in Global Jukebox online, though it is in the database. | AJ99: 43286.433 | AK99: MJW
A100: =VLOOKUP(H100,Languages!$A$2:$B$430,2,FALSE) -> Afro-Asiatic | B100: Story | C100: Northern Africa | D100: Sahrawi: Hassaniya | E100: hass1238 | F100: arab1395 | G100: hass1238 | H100: =VLOOKUP(G100,'languoid 4.0'!$A$1:$I$24439,2,FALSE) -> afro1255 | I100: =VLOOKUP(G100,'languoid 4.0'!$A$1:$I$24439,6,FALSE) -> language | J100: no | K100: yes | L100: yes | N100: mey | O100: Exact Match | P100: I'm sure | Q100: Teiduma | R100: https://sounds.bl.uk/World-and-traditional-music/Violeta-Ruano-portraits-of-Saharawi-Music/025M-C1640X0055XX-0001V0 | S100: NA | T100: British Library | U100: Love | V100: No | Z100: There is text in associated ethnography that states what type of song this is (this could be in liner notes, it could be in an email from an anthropologist, etc) | AA100: NA | AB100: This song is a traditional tune from the repertoire of the lashuar, or shadow music, which was performed during the day, when the sun still makes shadows. It talks about a tree named teiduma. Somebody loves a woman that he encounters under a tree. When he comes back to the same spot, she is not there anymore and the tree is dead. These songs were usually performed at family or other social events. The performance occasion was a private session organised by the musician in her house. Tarba Bueibu normally performs at national events with the national opera, but she does not consider herself a professional musician. She was playing a plastic bucket as a drum. //BRITISH LIBRARY SHELF MARK: C1640/55, COLLECTION: VIOLETA RUANO PORTRAITS OF SAHARAWI MUSIC, CATEGORY: LOVE SONGS, TITLE: TEIDUMA, ABSTRACT // | AC100: NA | AE100: I followed the instructions and I have not yet listened to it! | AF100: Yes | AG100: 6 | AH100: Yes | AJ100: 43317.727 | AK100: MJW
...

Sheet languoid 4.0
A1: id | B1: family_id | C1: parent_id | D1: name | E1: bookkeeping | F1: level | G1: latitude | H1: longitude | I1: iso639P3code | J1: description | K1: markup_description | L1: child_family_count | M1: child_language_count | N1: child_dialect_count | O1: country_ids
A2: 3adt1234 | B2: afro1255 | C2: nort3292 | D2: 3Ad-Tekles | E2: FALSE | F2: dialect | L2: 0 | M2: 0 | N2: 0
A3: aala1237 | B3: aust1307 | C3: ramo1244 | D3: Aalawa | E3: FALSE | F3: dialect | L3: 0 | M3: 0 | N3: 0
A4: aant1238 | B4: nucl1709 | C4: nort2920 | D4: Aantantara | E4: FALSE | F4: dialect | L4: 0 | M4: 0 | N4: 0
A5: aari1238 | B5: sout2845 | C5: ahkk1235 | D5: Aari-Gayil | E5: FALSE | F5: family | I5: aiz | L5: 0 | M5: 2 | N5: 0
A6: aari1239 | B6: sout2845 | C6: aari1238 | D6: Aari | E6: FALSE | F6: language | G6: 5.95034 | H6: 36.5721 | I6: aiw | L6: 0 | M6: 0 | N6: 0 | O6: ET
A7: aari1240 | B7: book1242 | C7: book1242 | D7: Aariya | E7: TRUE | F7: language | I7: aay | L7: 0 | M7: 0 | N7: 0 | O7: IN
A8: aasa1238 | B8: afro1255 | C8: unun9872 | D8: Aasax | E8: FALSE | F8: language | G8: -4.00679 | H8: 36.8648 | I8: aas | L8: 0 | M8: 0 | N8: 0 | O8: TZ
A9: aasd1234 | B9: indo1319 | C9: ferr1240 | D9: Aasdring | E9: FALSE | F9: dialect | L9: 0 | M9: 0 | N9: 0
A10: aata1238 | B10: nucl1709 | C10: sout2943 | D10: Aatasaara | E10: FALSE | F10: dialect | L10: 0 | M10: 0 | N10: 0
A11: abaa1238 | B11: sino1245 | C11: nort3305 | D11: Rngaba | E11: FALSE | F11: dialect | L11: 0 | M11: 0 | N11: 0
A12: abab1239 | B12: afro1255 | C12: beja1238 | D12: Ababda | E12: FALSE | F12: dialect | L12: 0 | M12: 0 | N12: 0
A13: abab1240 | B13: atla1278 | C13: narr1281 | D13: Ababuan | E13: FALSE | F13: family | L13: 13 | M13: 22 | N13: 29
A14: abad1240 | B14: abkh1242 | C14: adyg1241 | D14: Abadzex | E14: FALSE | F14: dialect | L14: 0 | M14: 0 | N14: 0
A15: abad1241 | B15: aust1307 | C15: west2850 | D15: Abadi | E15: FALSE | F15: language | G15: -9.03389 | H15: 146.992 | I15: kbt | L15: 0 | M15: 0 | N15: 0 | O15: PG
A16: abag1245 | B16: nucl1709 | C16: unun9976 | D16: Abaga | E16: FALSE | F16: language | G16: -6.12028 | H16: 145.665 | I16: abg | L16: 0 | M16: 0 | N16: 0 | O16: PG
A17: abai1239 | B17: aust1307 | C17: lund1271 | D17: Abai | E17: FALSE | F17: dialect | L17: 0 | M17: 0 | N17: 0
A18: abai1240 | B18: aust1307 | C18: pait1248 | D18: Abai Sungai | E18: FALSE | F18: language | G18: 5.55394 | H18: 118.306 | I18: abf | L18: 0 | M18: 0 | N18: 0 | O18: MY
A19: abai1241 | B19: aust1307 | C19: muru1275 | D19: Abai Tubu-Abai Sembuak | E19: FALSE | F19: language | L19: 0 | M19: 0 | N19: 0 | O19: MY
A20: abak1242 | B20: atla1278 | C20: anaa1238 | D20: Abak | E20: FALSE | F20: dialect | L20: 0 | M20: 0 | N20: 0
A21: abak1243 | B21: aust1307 | C21: ilon1239 | D21: Abaka | E21: FALSE | F21: dialect | L21: 0 | M21: 0 | N21: 0
A22: abal1238 | B22: yele1255 | C22: yele1255 | D22: Abaletti | E22: FALSE | F22: dialect | L22: 0 | M22: 0 | N22: 0
A23: abam1239 | B23: east2503 | C23: wipi1242 | D23: Abam | E23: FALSE | F23: dialect | L23: 0 | M23: 0 | N23: 0
A24: aban1242 | B24: atla1278 | C24: aban1244 | D24: Abanyom | E24: FALSE | F24: language | G24: 6.30619 | H24: 8.63055 | I24: abm | L24: 0 | M24: 0 | N24: 0 | O24: NG
A25: aban1243 | B25: quec1387 | C25: east2551 | D25: Abancay | E25: FALSE | F25: dialect | L25: 0 | M25: 0 | N25: 0
A26: aban1244 | B26: atla1278 | C26: bako1254 | D26: Abanyom-Ekajuk | E26: FALSE | F26: family | L26: 0 | M26: 3 | N26: 0
A27: abar1238 | B27: atla1278 | C27: sout3152 | D27: Mungbam | E27: FALSE | F27: language | G27: 6.5805 | H27: 10.2267 | I27: mij | L27: 0 | M27: 0 | N27: 0 | O27: CM
A28: abau1245 | B28: sepi1257 | C28: sepi1257 | D28: Abau | E28: FALSE | F28: language | G28: -3.97222 | H28: 141.324 | I28: aau | L28: 0 | M28: 0 | N28: 0 | O28: PG
A29: abaw1238 | B29: atla1278 | C29: gupa1248 | D29: Abawa | E29: FALSE | F29: dialect | L29: 0 | M29: 0 | N29: 0
A30: abay1238 | B30: atla1278 | C30: agwa1247 | D30: Abayongo | E30: FALSE | F30: dialect | L30: 0 | M30: 0 | N30: 0
A31: abaz1241 | B31: abkh1242 | C31: abkh1243 | D31: Abaza | E31: FALSE | F31: language | G31: 41.1214 | H31: 42.7273 | I31: abq | L31: 0 | M31: 0 | N31: 3 | O31: RU TR
A32: abbe1238 | B32: atla1278 | C32: abee1242 | D32: Abbey-Ve | E32: FALSE | F32: dialect | L32: 0 | M32: 0 | N32: 0
A33: abbr1238 | B33: indo1319 | C33: sout3309 | D33: Abbruzzesi | E33: FALSE | F33: dialect | L33: 0 | M33: 0 | N33: 0
A34: abda1238 | B34: afro1255 | C34: soqo1240 | D34: 'Abd Al-Kuri | E34: FALSE | F34: dialect | L34: 0 | M34: 0 | N34: 0
A35: abed1238 | B35: cent2225 | C35: lugb1240 | D35: Abedju-Azaki | E35: FALSE | F35: dialect | L35: 0 | M35: 0 | N35: 0
A36: abee1242 | B36: atla1278 | C36: agne1238 | D36: Ab√© | E36: FALSE | F36: language | G36: 5.59682 | H36: -4.38497 | I36: aba | L36: 0 | M36: 0 | N36: 4 | O36: CI
A37: abee1243 | B37: atla1278 | C37: anyi1245 | D37: Abe (Anyin) | E37: FALSE | F37: dialect | L37: 0 | M37: 0 | N37: 0
A38: abel1234 | B38: aust1307 | C38: samb1319 | D38: Abellen-Botolan | E38: FALSE | F38: family | L38: 0 | M38: 2 | N38: 2
A39: aben1247 | B39: sino1245 | C39: garo1247 | D39: Abeng | E39: FALSE | F39: dialect | L39: 0 | M39: 0 | N39: 0
A40: aben1248 | B40: sino1245 | C40: garo1247 | D40: A'beng | E40: FALSE | F40: dialect | L40: 0 | M40: 0 | N40: 0
A41: aben1249 | B41: aust1307 | C41: abel1234 | D41: Abenlen Ayta | E41: FALSE | F41: language | G41: 15.4131 | H41: 120.2 | I41: abp | L41: 0 | M41: 0 | N41: 0 | O41: PH
A42: abgu1238 | B42: afro1255 | C42: birg1239 | D42: Abgue | E42: FALSE | F42: dialect | L42: 0 | M42: 0 | N42: 0
A43: abid1235 | B43: atla1278 | C43: agne1238 | D43: Abidji | E43: FALSE | F43: language | G43: 5.65656 | H43: -4.58421 | I43: abi | L43: 0 | M43: 0 | N43: 2 | O43: CI
A44: abie1238 | B44: nilo1247 | C44: sout2832 | D44: Abiem | E44: FALSE | F44: dialect | L44: 0 | M44: 0 | N44: 0
A45: abig1238 | B45: nilo1247 | C45: nuer1246 | D45: Abigar | E45: FALSE | F45: dialect | L45: 0 | M45: 0 | N45: 0
A46: abil1238 | B46: nilo1247 | C46: nort2815 | D46: Abiliang | E46: FALSE | F46: dialect | L46: 0 | M46: 0 | N46: 0
A47: abin1242 | B47: atla1278 | C47: agwa1247 | D47: Abini | E47: FALSE | F47: dialect | L47: 0 | M47: 0 | N47: 0
A48: abin1243 | D48: Abinomn | E48: FALSE | F48: language | G48: -2.92281 | H48: 138.891 | I48: bsa | L48: 0 | M48: 0 | N48: 0 | O48: ID
A49: abip1241 | B49: guai1249 | C49: guai1250 | D49: Abipon | E49: FALSE | F49: language | G49: -29 | H49: -61 | I49: axb | L49: 0 | M49: 0 | N49: 0 | O49: AR
A50: abis1238 | D50: Aewa | E50: FALSE | F50: language | G50: -1.284096 | H50: -75.084405 | I50: ash | L50: 0 | M50: 0 | N50: 0 | O50: PE
A51: abka1238 | B51: maba1274 | C51: maba1277 | D51: Abkar | E51: FALSE | F51: dialect | L51: 0 | M51: 0 | N51: 0
A52: abkh1242 | D52: Abkhaz-Adyge | E52: FALSE | F52: family | L52: 2 | M52: 5 | N52: 12
A53: abkh1243 | B53: abkh1242 | C53: abkh1242 | D53: Abkhaz-Abaza | E53: FALSE | F53: family | L53: 0 | M53: 2 | N53: 6
A54: abkh1244 | B54: abkh1242 | C54: abkh1243 | D54: Abkhazian | E54: FALSE | F54: language | G54: 43.056218 | H54: 41.159115 | I54: abk | L54: 0 | M54: 0 | N54: 3 | O54: GE RU TR
A55: able1237 | B55: aust1307 | C55: lubu1243 | D55: Ableg-Salegseg | E55: FALSE | F55: dialect | L55: 0 | M55: 0 | N55: 0
A56: abob1234 | B56: atla1278 | C56: basa1283 | D56: Abo-Barombi | E56: FALSE | F56: family | L56: 0 | M56: 2 | N56: 0
A57: abom1238 | B57: anim1240 | C57: tiri1259 | D57: Abom | E57: FALSE | F57: language | G57: -8.42448 | H57: 142.842 | I57: aob | L57: 0 | M57: 0 | N57: 0 | O57: PG
A58: abon1238 | B58: atla1278 | C58: nort3192 | D58: Abon | E58: FALSE | F58: language | G58: 6.90621 | H58: 10.8769 | I58: abo | L58: 0 | M58: 0 | N58: 0 | O58: CM NG
A59: aboo1241 | B59: atla1278 | C59: boky1238 | D59: Abo (Bokyi) | E59: FALSE | F59: dialect | L59: 0 | M59: 0 | N59: 0
A60: aboo1242 | B60: atla1278 | C60: ukwu1241 | D60: Abo | E60: FALSE | F60: dialect | L60: 0 | M60: 0 | N60: 0
A61: abou1238 | B61: tama1329 | C61: mara1396 | D61: Abou Charib | E61: FALSE | F61: dialect | L61: 0 | M61: 0 | N61: 0
A62: abra1237 | B62: aust1307 | C62: iray1237 | D62: Abra-De-Ilog | E62: FALSE | F62: dialect | L62: 0 | M62: 0 | N62: 0
A63: abro1238 | B63: atla1278 | C63: akan1251 | D63: Abron | E63: FALSE | F63: language | G63: 7.72094 | H63: -2.50289 | I63: abr | L63: 0 | M63: 0 | N63: 0 | O63: CI GH
A64: abru1239 | B64: indo1319 | C64: balk1252 | D64: Abruzzese-Calabrian-Molisean Romani | E64: FALSE | F64: dialect | L64: 0 | M64: 0 | N64: 0
A65: absh1238 | B65: indo1319 | C65: musl1236 | D65: Absheron | E65: FALSE | F65: dialect | L65: 0 | M65: 0 | N65: 0
A66: abua1243 | B66: atla1278 | C66: cent2028 | D66: Abua-Odual | E66: FALSE | F66: family | L66: 0 | M66: 2 | N66: 6
A67: abua1244 | B67: atla1278 | C67: abua1243 | D67: Abua | E67: FALSE | F67: language | G67: 4.83057 | H67: 6.61492 | I67: abn | L67: 0 | M67: 0 | N67: 4 | O67: NG
A68: abua1245 | B68: nucl1708 | C68: buki1250 | D68: Abu' Arapesh | E68: FALSE | F68: language | G68: -3.461612 | H68: 142.91703 | I68: aah | L68: 0 | M68: 0 | N68: 0 | O68: PG
A69: abui1241 | B69: timo1261 | C69: alor1250 | D69: Abui | E69: FALSE | F69: language | G69: -8.31058 | H69: 124.588 | I69: abz | L69: 0 | M69: 0 | N69: 3 | O69: ID
A70: abuj1237 | B70: drav1251 | C70: mari1414 | D70: Abujmaria | E70: FALSE | F70: dialect | L70: 0 | M70: 0 | N70: 0
A71: abul1238 | B71: nilo1247 | C71: buru1301 | D71: Abuldugu | E71: FALSE | F71: dialect | L71: 0 | M71: 0 | N71: 0
A72: abun1252 | D72: Abun | E72: FALSE | F72: language | G72: -0.57073 | H72: 132.416 | I72: kgr | L72: 0 | M72: 0 | N72: 3 | O72: ID
A73: abun1253 | B73: abun1252 | C73: abun1252 | D73: Abun Je | E73: FALSE | F73: dialect | L73: 0 | M73: 0 | N73: 0
A74: abun1254 | B74: abun1252 | C74: abun1252 | D74: Abun Tat | E74: FALSE | F74: dialect | L74: 0 | M74: 0 | N74: 0
A75: abun1255 | B75: abun1252 | C75: abun1252 | D75: Abun Ji | E75: FALSE | F75: dialect | L75: 0 | M75: 0 | N75: 0
A76: abur1243 | B76: atla1278 | C76: west2816 | D76: Abure | E76: FALSE | F76: language | G76: 5.21534 | H76: -3.64123 | I76: abu | L76: 0 | M76: 0 | N76: 0 | O76: CI
A77: abur1244 | B77: atla1278 | C77: kugb1242 | D77: Abureni | E77: FALSE | F77: language | G77: 4.62301 | H77: 6.50634 | I77: mgj | L77: 0 | M77: 0 | N77: 0 | O77: NG
A78: abus1238 | B78: kadu1256 | C78: kang1288 | D78: Abu Sinun | E78: FALSE | F78: dialect | L78: 0 | M78: 0 | N78: 0
A79: abuu1241 | B79: lowe1437 | C79: agoa1234 | D79: Abu | E79: FALSE | F79: language | G79: -4.24027 | H79: 144.474 | I79: ado | L79: 0 | M79: 0 | N79: 3 | O79: PG
A80: abzh1238 | B80: abkh1242 | C80: abkh1244 | D80: Abzhui | E80: FALSE | F80: dialect | L80: 0 | M80: 0 | N80: 0
A81: acad1238 | B81: indo1319 | C81: stan1290 | D81: Acadian | E81: FALSE | F81: dialect | L81: 0 | M81: 0 | N81: 0
A82: acat1239 | B82: otom1299 | C82: meph1234 | D82: Acatepec Me'phaa | E82: FALSE | F82: language | G82: 17.1034 | H82: -99.0602 | I82: tpx | L82: 0 | M82: 0 | N82: 3 | O82: MX
A83: acat1240 | B83: otom1299 | C83: acat1239 | D83: Acatepec | E83: FALSE | F83: dialect | L83: 0 | M83: 0 | N83: 0
A84: acch1238 | B84: indo1319 | C84: nepa1254 | D84: Acchami | E84: FALSE | F84: dialect | L84: 0 | M84: 0 | N84: 0
A85: acha1249 | B85: sino1245 | C85: acha1252 | D85: Longchuan Achang | E85: FALSE | F85: language | G85: 24.3479 | H85: 97.7438 | I85: acn | L85: 0 | M85: 0 | N85: 3 | O85: CN MM
A86: acha1250 | B86: araw1281 | C86: piap1247 | D86: Achagua | E86: FALSE | F86: language | G86: 4.38649 | H86: -72.2005 | I86: aca | L86: 0 | M86: 0 | N86: 0 | O86: CO
A87: acha1252 | B87: sino1245 | C87: high1273 | D87: Achangic | E87: FALSE | F87: family | L87: 0 | M87: 4 | N87: 3
A88: ache1244 | B88: sino1245 | C88: unun9958 | D88: Ache | E88: FALSE | F88: language | G88: 24.152 | H88: 102.446 | I88: yif | L88: 0 | M88: 0 | N88: 0 | O88: CN
A89: ache1245 | B89: narr1279 | C89: ache1247 | D89: Acheron | E89: FALSE | F89: language | G89: 10.8827 | H89: 30.3187 | I89: acz | L89: 0 | M89: 0 | N89: 2 | O89: SD
A90: ache1246 | B90: tupi1275 | C90: tupi1277 | D90: Ach√© | E90: FALSE | F90: language | G90: -25.5865 | H90: -56.4697 | I90: guq | L90: 0 | M90: 0 | N90: 0 | O90: PY
A91: ache1247 | B91: narr1279 | C91: bura1298 | D91: Acheron-Tocho | E91: FALSE | F91: family | L91: 0 | M91: 2 | N91: 2
A92: achi1247 | B92: sino1245 | C92: garo1247 | D92: Achik | E92: FALSE | F92: dialect | L92: 0 | M92: 0 | N92: 0
A93: achi1255 | B93: sino1245 | C93: garo1247 | D93: A'chick | E93: FALSE | F93: dialect | L93: 0 | M93: 0 | N93: 0
A94: achi1256 | B94: maya1287 | C94: quic1275 | D94: Achi | E94: FALSE | F94: language | G94: 15.073 | H94: -90.3513 | I94: acr | L94: 0 | M94: 0 | N94: 0 | O94: GT
A95: achi1257 | B95: aust1307 | C95: cham1327 | D95: Acehnese | E95: FALSE | F95: language | G95: 3.90757 | H95: 96.6032 | I95: ace | L95: 0 | M95: 0 | N95: 7 | O95: ID
A96: achi1258 | B96: book1242 | C96: book1242 | D96: Achi', Cubulco | E96: TRUE | F96: language | I96: acc | L96: 0 | M96: 0 | N96: 0 | O96: GT
A97: acht1238 | B97: indo1319 | C97: west2356 | D97: Achterhoeks | E97: FALSE | F97: dialect | G97: 52.021 | H97: 6.47521 | I97: act | L97: 0 | M97: 0 | N97: 0 | O97: DE NL
A98: achu1247 | B98: pala1350 | C98: pala1350 | D98: Achumawi | E98: FALSE | F98: language | G98: 41.0979 | H98: -121.191 | I98: acv | L98: 0 | M98: 0 | N98: 0 | O98: US
A99: achu1248 | B99: jiva1245 | C99: shua1256 | D99: Achuar-Shiwiar | E99: FALSE | F99: language | G99: -2.82646 | H99: -77.2641 | I99: acu | L99: 0 | M99: 0 | N99: 2 | O99: EC PE
A100: achu1249 | B100: jiva1245 | C100: achu1248 | D100: Achuar | E100: FALSE | F100: dialect | L100: 0 | M100: 0 | N100: 0
...

Sheet Languages
A1: ID | B1: Name | C1: Latitude | D1: Longitude
A2: atla1278 | B2: =HYPERLINK("https://glottolog.org/resource/languoid/id/atla1278","Atlantic-Congo") -> Atlantic-Congo
A3: aust1307 | B3: =HYPERLINK("https://glottolog.org/resource/languoid/id/aust1307","Austronesian") -> Austronesian
A4: indo1319 | B4: =HYPERLINK("https://glottolog.org/resource/languoid/id/indo1319","Indo-European") -> Indo-European
A5: sino1245 | B5: =HYPERLINK("https://glottolog.org/resource/languoid/id/sino1245","Sino-Tibetan") -> Sino-Tibetan
A6: book1242 | B6: =HYPERLINK("https://glottolog.org/resource/languoid/id/book1242","Bookkeeping") -> Bookkeeping
A7: afro1255 | B7: =HYPERLINK("https://glottolog.org/resource/languoid/id/afro1255","Afro-Asiatic") -> Afro-Asiatic
A8: nucl1709 | B8: =HYPERLINK("https://glottolog.org/resource/languoid/id/nucl1709","Nuclear Trans New Guinea") -> Nuclear Trans New Guinea
A9: pama1250 | B9: =HYPERLINK("https://glottolog.org/resource/languoid/id/pama1250","Pama-Nyungan") -> Pama-Nyungan
A10: sign1238 | B10: =HYPERLINK("https://glottolog.org/resource/languoid/id/sign1238","Sign Language") -> Sign Language
A11: otom1299 | B11: =HYPERLINK("https://glottolog.org/resource/languoid/id/otom1299","Otomanguean") -> Otomanguean
A12: aust1305 | B12: =HYPERLINK("https://glottolog.org/resource/languoid/id/aust1305","Austroasiatic") -> Austroasiatic
A13: uncl1493 | B13: =HYPERLINK("https://glottolog.org/resource/languoid/id/uncl1493","Unclassifiable") -> Unclassifiable
A14: taik1256 | B14: =HYPERLINK("https://glottolog.org/resource/languoid/id/taik1256","Tai-Kadai") -> Tai-Kadai
A15: drav1251 | B15: =HYPERLINK("https://glottolog.org/resource/languoid/id/drav1251","Dravidian") -> Dravidian
A16: pidg1258 | B16: =HYPERLINK("https://glottolog.org/resource/languoid/id/pidg1258","Pidgin") -> Pidgin
A17: araw1281 | B17: =HYPERLINK("https://glottolog.org/resource/languoid/id/araw1281","Arawakan") -> Arawakan
A18: mand1469 | B18: =HYPERLINK("https://glottolog.org/resource/languoid/id/mand1469","Mande") -> Mande
A19: tupi1275 | B19: =HYPERLINK("https://glottolog.org/resource/languoid/id/tupi1275","Tupian") -> Tupian
A20: utoa1244 | B20: =HYPERLINK("https://glottolog.org/resource/languoid/id/utoa1244","Uto-Aztecan") -> Uto-Aztecan
A21: unat1236 | B21: =HYPERLINK("https://glottolog.org/resource/languoid/id/unat1236","Unattested") -> Unattested
A22: cent2225 | B22: =HYPERLINK("https://glottolog.org/resource/languoid/id/cent2225","Central Sudanic") -> Central Sudanic
A23: nucl1708 | B23: =HYPERLINK("https://glottolog.org/resource/languoid/id/nucl1708","Nuclear Torricelli") -> Nuclear Torricelli
A24: nilo1247 | B24: =HYPERLINK("https://glottolog.org/resource/languoid/id/nilo1247","Nilotic") -> Nilotic
A25: ural1272 | B25: =HYPERLINK("https://glottolog.org/resource/languoid/id/ural1272","Uralic") -> Uralic
A26: algi1248 | B26: =HYPERLINK("https://glottolog.org/resource/languoid/id/algi1248","Algic") -> Algic
A27: atha1245 | B27: =HYPERLINK("https://glottolog.org/resource/languoid/id/atha1245","Athabaskan-Eyak-Tlingit") -> Athabaskan-Eyak-Tlingit
A28: pano1259 | B28: =HYPERLINK("https://glottolog.org/resource/languoid/id/pano1259","Pano-Tacanan") -> Pano-Tacanan
A29: quec1387 | B29: =HYPERLINK("https://glottolog.org/resource/languoid/id/quec1387","Quechuan") -> Quechuan
A30: turk1311 | B30: =HYPERLINK("https://glottolog.org/resource/languoid/id/turk1311","Turkic") -> Turkic
A31: cari1283 | B31: =HYPERLINK("https://glottolog.org/resource/languoid/id/cari1283","Cariban") -> Cariban
A32: hmon1336 | B32: =HYPERLINK("https://glottolog.org/resource/languoid/id/hmon1336","Hmong-Mien") -> Hmong-Mien
A33: sepi1257 | B33: =HYPERLINK("https://glottolog.org/resource/languoid/id/sepi1257","Sepik") -> Sepik
A34: nakh1245 | B34: =HYPERLINK("https://glottolog.org/resource/languoid/id/nakh1245","Nakh-Daghestanian") -> Nakh-Daghestanian
A35: maya1287 | B35: =HYPERLINK("https://glottolog.org/resource/languoid/id/maya1287","Mayan") -> Mayan
A36: lowe1437 | B36: =HYPERLINK("https://glottolog.org/resource/languoid/id/lowe1437","Lower Sepik-Ramu") -> Lower Sepik-Ramu
A37: nucl1710 | B37: =HYPERLINK("https://glottolog.org/resource/languoid/id/nucl1710","Nuclear-Macro-Je") -> Nuclear-Macro-Je
A38: chib1249 | B38: =HYPERLINK("https://glottolog.org/resource/languoid/id/chib1249","Chibchan") -> Chibchan
A39: tuca1253 | B39: =HYPERLINK("https://glottolog.org/resource/languoid/id/tuca1253","Tucanoan") -> Tucanoan
A40: sali1255 | B40: =HYPERLINK("https://glottolog.org/resource/languoid/id/sali1255","Salishan") -> Salishan
A41: mixe1287 | B41: =HYPERLINK("https://glottolog.org/resource/languoid/id/mixe1287","Mixed Language") -> Mixed Language
A42: timo1261 | B42: =HYPERLINK("https://glottolog.org/resource/languoid/id/timo1261","Timor-Alor-Pantar") -> Timor-Alor-Pantar
A43: dogo1299 | B43: =HYPERLINK("https://glottolog.org/resource/languoid/id/dogo1299","Dogon") -> Dogon
A44: lake1255 | B44: =HYPERLINK("https://glottolog.org/resource/languoid/id/lake1255","Lakes Plain") -> Lakes Plain
A45: mixe1284 | B45: =HYPERLINK("https://glottolog.org/resource/languoid/id/mixe1284","Mixe-Zoque") -> Mixe-Zoque
A46: more1255 | B46: =HYPERLINK("https://glottolog.org/resource/languoid/id/more1255","Morehead-Wasur") -> Morehead-Wasur
A47: gong1255 | B47: =HYPERLINK("https://glottolog.org/resource/languoid/id/gong1255","Ta-Ne-Omotic") -> Ta-Ne-Omotic
A48: siou1252 | B48: =HYPERLINK("https://glottolog.org/resource/languoid/id/siou1252","Siouan") -> Siouan
A49: anim1240 | B49: =HYPERLINK("https://glottolog.org/resource/languoid/id/anim1240","Anim") -> Anim
A50: mong1329 | B50: =HYPERLINK("https://glottolog.org/resource/languoid/id/mong1329","Mongolic") -> Mongolic
A51: arti1236 | B51: =HYPERLINK("https://glottolog.org/resource/languoid/id/arti1236","Artificial Language") -> Artificial Language
A52: bord1247 | B52: =HYPERLINK("https://glottolog.org/resource/languoid/id/bord1247","Border") -> Border
A53: japo1237 | B53: =HYPERLINK("https://glottolog.org/resource/languoid/id/japo1237","Japonic") -> Japonic
A54: nort2923 | B54: =HYPERLINK("https://glottolog.org/resource/languoid/id/nort2923","North Halmahera") -> North Halmahera
A55: khoe1240 | B55: =HYPERLINK("https://glottolog.org/resource/languoid/id/khoe1240","Khoe-Kwadi") -> Khoe-Kwadi
A56: anga1289 | B56: =HYPERLINK("https://glottolog.org/resource/languoid/id/anga1289","Angan") -> Angan
A57: nduu1242 | B57: =HYPERLINK("https://glottolog.org/resource/languoid/id/nduu1242","Ndu") -> Ndu
A58: nubi1251 | B58: =HYPERLINK("https://glottolog.org/resource/languoid/id/nubi1251","Nubian") -> Nubian
A59: toro1256 | B59: =HYPERLINK("https://glottolog.org/resource/languoid/id/toro1256","Tor-Orya") -> Tor-Orya
A60: tung1282 | B60: =HYPERLINK("https://glottolog.org/resource/languoid/id/tung1282","Tungusic") -> Tungusic
A61: chap1271 | B61: =HYPERLINK("https://glottolog.org/resource/languoid/id/chap1271","Chapacuran") -> Chapacuran
A62: eski1264 | B62: =HYPERLINK("https://glottolog.org/resource/languoid/id/eski1264","Eskimo-Aleut") -> Eskimo-Aleut
A63: gunw1250 | B63: =HYPERLINK("https://glottolog.org/resource/languoid/id/gunw1250","Gunwinyguan") -> Gunwinyguan
A64: toto1251 | B64: =HYPERLINK("https://glottolog.org/resource/languoid/id/toto1251","Totonacan") -> Totonacan
A65: coch1271 | B65: =HYPERLINK("https://glottolog.org/resource/languoid/id/coch1271","Cochimi-Yuman") -> Cochimi-Yuman
A66: iroq1247 | B66: =HYPERLINK("https://glottolog.org/resource/languoid/id/iroq1247","Iroquoian") -> Iroquoian
A67: miwo1274 | B67: =HYPERLINK("https://glottolog.org/resource/languoid/id/miwo1274","Miwok-Costanoan") -> Miwok-Costanoan
A68: surm1244 | B68: =HYPERLINK("https://glottolog.org/resource/languoid/id/surm1244","Surmic") -> Surmic
A69: west2434 | B69: =HYPERLINK("https://glottolog.org/resource/languoid/id/west2434","Western Daly") -> Western Daly
A70: geel1240 | B70: =HYPERLINK("https://glottolog.org/resource/languoid/id/geel1240","Geelvink Bay") -> Geelvink Bay
A71: grea1241 | B71: =HYPERLINK("https://glottolog.org/resource/languoid/id/grea1241","Great Andamanese") -> Great Andamanese
A72: heib1242 | B72: =HYPERLINK("https://glottolog.org/resource/languoid/id/heib1242","Heibanic") -> Heibanic
A73: ijoi1239 | B73: =HYPERLINK("https://glottolog.org/resource/languoid/id/ijoi1239","Ijoid") -> Ijoid
A74: maba1274 | B74: =HYPERLINK("https://glottolog.org/resource/languoid/id/maba1274","Maban") -> Maban
A75: nyul1248 | B75: =HYPERLINK("https://glottolog.org/resource/languoid/id/nyul1248","Nyulnyulan") -> Nyulnyulan
A76: saha1256 | B76: =HYPERLINK("https://glottolog.org/resource/languoid/id/saha1256","Saharan") -> Saharan
A77: skoo1245 | B77: =HYPERLINK("https://glottolog.org/resource/languoid/id/skoo1245","Sko") -> Sko
A78: song1307 | B78: =HYPERLINK("https://glottolog.org/resource/languoid/id/song1307","Songhay") -> Songhay
A79: worr1236 | B79: =HYPERLINK("https://glottolog.org/resource/languoid/id/worr1236","Worrorran") -> Worrorran
A80: choc1280 | B80: =HYPERLINK("https://glottolog.org/resource/languoid/id/choc1280","Chocoan") -> Chocoan
A81: daga1274 | B81: =HYPERLINK("https://glottolog.org/resource/languoid/id/daga1274","Dagan") -> Dagan
A82: sout2948 | B82: =HYPERLINK("https://glottolog.org/resource/languoid/id/sout2948","South Bougainville") -> South Bougainville
A83: kwer1242 | B83: =HYPERLINK("https://glottolog.org/resource/languoid/id/kwer1242","Greater Kwerba") -> Greater Kwerba
A84: kiow1265 | B84: =HYPERLINK("https://glottolog.org/resource/languoid/id/kiow1265","Kiowa-Tanoan") -> Kiowa-Tanoan
A85: koia1260 | B85: =HYPERLINK("https://glottolog.org/resource/languoid/id/koia1260","Koiarian") -> Koiarian
A86: mail1249 | B86: =HYPERLINK("https://glottolog.org/resource/languoid/id/mail1249","Mailuan") -> Mailuan
A87: narr1279 | B87: =HYPERLINK("https://glottolog.org/resource/languoid/id/narr1279","Narrow Talodi") -> Narrow Talodi
A88: tuuu1241 | B88: =HYPERLINK("https://glottolog.org/resource/languoid/id/tuuu1241","Tuu") -> Tuu
A89: bosa1245 | B89: =HYPERLINK("https://glottolog.org/resource/languoid/id/bosa1245","Bosavi") -> Bosavi
A90: chuk1271 | B90: =HYPERLINK("https://glottolog.org/resource/languoid/id/chuk1271","Chukotko-Kamchatkan") -> Chukotko-Kamchatkan
A91: daju1249 | B91: =HYPERLINK("https://glottolog.org/resource/languoid/id/daju1249","Dajuic") -> Dajuic
A92: huit1251 | B92: =HYPERLINK("https://glottolog.org/resource/languoid/id/huit1251","Huitotoan") -> Huitotoan
A93: mata1289 | B93: =HYPERLINK("https://glottolog.org/resource/languoid/id/mata1289","Matacoan") -> Matacoan
A94: musk1252 | B94: =HYPERLINK("https://glottolog.org/resource/languoid/id/musk1252","Muskogean") -> Muskogean
A95: pomo1273 | B95: =HYPERLINK("https://glottolog.org/resource/languoid/id/pomo1273","Pomoan") -> Pomoan
A96: spee1234 | B96: =HYPERLINK("https://glottolog.org/resource/languoid/id/spee1234","Speech Register") -> Speech Register
A97: araw1282 | B97: =HYPERLINK("https://glottolog.org/resource/languoid/id/araw1282","Arawan") -> Arawan
A98: bain1263 | B98: =HYPERLINK("https://glottolog.org/resource/languoid/id/bain1263","Baining") -> Baining
A99: barb1265 | B99: =HYPERLINK("https://glottolog.org/resource/languoid/id/barb1265","Barbacoan") -> Barbacoan
A100: chum1262 | B100: =HYPERLINK("https://glottolog.org/resource/languoid/id/chum1262","Chumashan") -> Chumashan
...
